{
    "id": 417240,
    "headword": "Dagfinn Instanes",
    "custom_metadata_json": {
        "professions": [
            {
                "description": "keramiker"
            }
        ],
        "others": [],
        "relations": [
            {
                "type": "Sønn av",
                "external_id": "person_8736ab103809",
                "birth_date": "",
                "death_date": "",
                "firstname": "Nils",
                "lastname": "Instanes",
                "professions": []
            },
            {
                "type": "Sønn av",
                "external_id": "person_8736ab103810",
                "birth_date": "",
                "death_date": "",
                "firstname": "Kristi",
                "lastname": "Sandven",
                "professions": []
            },
            {
                "type": "Gift med",
                "external_id": "person_8736ab103811",
                "birth_date": "",
                "death_date": "",
                "firstname": "Margreta",
                "lastname": "Haustveit",
                "professions": []
            }
        ],
        "residences": [
            {
                "order": "0",
                "description": "Grimo i Hardanger"
            }
        ],
        "educations": [
            {
                "comment": "praksis ved Den Kongelige Porcelainsfabrik, København",
                "order": "2"
            },
            {
                "comment": "Statens Håndverks- og Kunstindustriskole",
                "order": "0"
            },
            {
                "comment": "verkstedspraksis i Drammen",
                "order": "1"
            }
        ],
        "travels": [
            {
                "order": "0",
                "description": "Stipend fra Fondet for dansk-norsk samarbeid 1956, -63"
            },
            {
                "order": "1",
                "description": "Bosatt en tid i København"
            }
        ],
        "memberships": [],
        "awards": [],
        "public_productions": [
            {
                "from_date": "",
                "order": "4",
                "to_date": "",
                "description": "Eidfjord samfunnshus (1982)"
            },
            {
                "from_date": "",
                "order": "1",
                "to_date": "",
                "description": "Hauso samfunnshus og Hauso barneskole, Hordaland"
            },
            {
                "from_date": "",
                "order": "5",
                "to_date": "",
                "description": "Eidfjord nye kirke (1981)"
            },
            {
                "from_date": "",
                "order": "0",
                "to_date": "",
                "description": "Kinsarvik herredshus (1978–79)"
            },
            {
                "from_date": "",
                "order": "2",
                "to_date": "",
                "description": "Kinsarvik ungdomsskole"
            },
            {
                "from_date": "",
                "order": "6",
                "to_date": "",
                "description": "flere offentlige bygg i Hordaland"
            },
            {
                "from_date": "",
                "order": "3",
                "to_date": "",
                "description": "Ullensvang herredshus (1980)"
            },
            {
                "from_date": "",
                "order": "7",
                "to_date": "",
                "description": "Vestlandske Kunstindustrimuseum, Bergen"
            }
        ],
        "performed_productions": [],
        "illustrations": [],
        "exhibitions": [
            {
                "category": "Kollektiv",
                "exhibition_organizer": "Bergen",
                "from_date": "1972",
                "order": "2",
                "to_date": ""
            },
            {
                "category": "Separat",
                "exhibition_organizer": "Vestlandske Kunstindustrimuseum, Bergen",
                "from_date": "1979",
                "order": "1",
                "to_date": ""
            },
            {
                "category": "Kollektiv",
                "exhibition_organizer": "Bergen",
                "from_date": "1950",
                "order": "3",
                "to_date": "1960",
                "title": "Brukskunstutst."
            },
            {
                "category": "Kollektiv",
                "exhibition_organizer": "Stavanger",
                "from_date": "1950",
                "order": "4",
                "to_date": "1960",
                "title": "Brukskunstutst."
            },
            {
                "category": "Kollektiv",
                "exhibition_organizer": "Oslo",
                "from_date": "1950",
                "order": "5",
                "to_date": "1960",
                "title": "Brukskunstutst."
            },
            {
                "category": "Separat",
                "exhibition_organizer": "Vestlandske Kunstindustrimuseum, Bergen",
                "from_date": "1965",
                "order": "0",
                "to_date": ""
            }
        ],
        "portraits": [],
        "authorships": [],
        "publishings": [
            {
                "from_date": "1979-11-10",
                "order": "4",
                "reference": "(ill.)",
                "to_date": "",
                "description": "Dagen",
                "authors": [],
                "comments": [],
                "archives": []
            },
            {
                "from_date": "1978-06-10",
                "order": "3",
                "to_date": "",
                "description": "Bergens Tidende.",
                "authors": [],
                "comments": [],
                "archives": []
            },
            {
                "from_date": "1972-05-31",
                "order": "2",
                "to_date": "",
                "description": "Hardanger Folkebl.",
                "authors": [],
                "comments": [],
                "archives": []
            },
            {
                "from_date": "",
                "optional_reference": "[u.å.] s. 44 (ill.)",
                "order": "0",
                "to_date": "",
                "description": "Norwegian Arts and Crafts, Industrial Design",
                "place": "Oslo",
                "authors": [
                    "Aars, F."
                ],
                "comments": [],
                "archives": []
            },
            {
                "from_date": "1964",
                "order": "1",
                "reference": "s. 27",
                "to_date": "",
                "description": "Landsforbundet Norsk Brukskunst årbok",
                "authors": [],
                "comments": [],
                "archives": []
            }
        ],
        "archives": [],
        "radio_and_tv_programs": []
    },
    "title": "Dagfinn Instanes",
    "url": "https://nkl.snl.no/Dagfinn_Instanes",
    "subject_url": "http://snl.no/.taxonomy/3405",
    "subject_title": "Norsk kunstnerleksikon",
    "xhtml_body": "<div><p>I. har laget krukker, boller, fat og skåler og en rekke relieffer og større og mindre skulpturer i steingods. Han har hatt flere større utsmykkingsoppgaver på Vestlandet, bl.a. keramikkutsmykking til herredshuset i Kinsarvik (1978–79). Han har også tegnet utkast til billedvev. I. har hatt eget verksted i Hardanger fra 1949.</p></div>",
    "created_at": "2013-07-03T20:17:50.741+02:00",
    "changed_at": "2024-06-18T23:26:02.373+02:00",
    "license_name": "begrenset",
    "metadata_license_name": "fri",
    "metadata": {
        "gender": "m",
        "same_as": "[\"http://data.nasjonalmuseet.no/resource/person_8736ab1837\",\"https://digitaltmuseum.no/606c39d4-ffff-4a93-b747-d31253fc9a42\",\"http://kulturnav.org/606c39d4-ffff-4a93-b747-d31253fc9a42\"]",
        "lastname": "Instanes",
        "firstname": "Dagfinn",
        "birth_date": "24.10.1919",
        "birthplace": "Grimo",
        "death_date": "0.0.1998",
        "external_id": "person_8736ab1837",
        "kulturnav_id": "606c39d4-ffff-4a93-b747-d31253fc9a42"
    },
    "authors": [
        {
            "full_name": "Glenny Alfsen"
        }
    ],
    "images": [],
    "professions": [
        {
            "description": "keramiker"
        }
    ]
}