{
    "id": 430955,
    "headword": "Jacob Christian Tokle",
    "custom_metadata_json": {
        "professions": [
            {
                "description": "rosemaler"
            }
        ],
        "others": [],
        "relations": [
            {
                "type": "Sønn av",
                "external_id": "person_8736ab108281",
                "birth_date": "1755",
                "death_date": "",
                "firstname": "Ellen Dorothea",
                "lastname": "Teilgaard",
                "professions": []
            },
            {
                "type": "Sønn av",
                "external_id": "person_8736ab108280",
                "birth_date": "",
                "death_date": "",
                "firstname": "Elling Pedersen",
                "lastname": "Tokle",
                "professions": []
            }
        ],
        "residences": [],
        "educations": [],
        "travels": [],
        "memberships": [],
        "awards": [],
        "public_productions": [
            {
                "from_date": "",
                "order": "0",
                "to_date": "",
                "description": "Representert i NF."
            }
        ],
        "performed_productions": [],
        "illustrations": [],
        "exhibitions": [],
        "portraits": [],
        "authorships": [],
        "publishings": [],
        "archives": [],
        "radio_and_tv_programs": []
    },
    "title": "Jacob Christian Tokle",
    "url": "https://nkl.snl.no/Jacob_Christian_Tokle",
    "subject_url": "http://snl.no/.taxonomy/3405",
    "subject_title": "Norsk kunstnerleksikon",
    "xhtml_body": "<div><p>I slekta til T. var det fleire målarar som kan ha verka inspirerande på arbeida hans, bl.a. oldefaren Rasmus Jacobsen Teilgaard, men ingen læremeister er kjend. I tida 1815-40 måla T. fleire kister og var den mest markante rosemålaren på Nordmøre. Stilen hans er særeigen med symmetriske komposisjonar av fjærliknande blad i C-formar rygg mot rygg. Fargane er kraftige, men godt avstemte på mørk blå eller grøn botn. T. var aktiv på fleire felt og samla og skreiv ned eventyr og sagn, interesserte seg for hagebruk og fruktdyrking, og sat som ordførar i Stangvik 1844-45.</p></div>",
    "created_at": "2014-12-19T16:26:45.077+01:00",
    "changed_at": "2024-06-18T23:28:11.162+02:00",
    "license_name": "begrenset",
    "metadata_license_name": "fri",
    "metadata": {
        "gender": "k",
        "same_as": "[\"http://data.nasjonalmuseet.no/resource/person_8736ab3765\",\"https://digitaltmuseum.no/35e18db2-5e43-4347-8109-b15d0a9629be\",\"http://kulturnav.org/35e18db2-5e43-4347-8109-b15d0a9629be\"]",
        "lastname": "Tokle",
        "firstname": "Jacob Christian",
        "birth_date": "0.0.1783",
        "birthplace": " Stangvik trolig",
        "death_date": "0.0.1853",
        "external_id": "person_8736ab3765",
        "kulturnav_id": "35e18db2-5e43-4347-8109-b15d0a9629be",
        "place_of_death": "samme sted"
    },
    "authors": [
        {
            "full_name": "Ola Grefstad"
        }
    ],
    "images": [],
    "professions": [
        {
            "description": "rosemaler"
        }
    ]
}