{
    "id": 417674,
    "headword": "Mari Foss",
    "custom_metadata_json": {
        "professions": [
            {
                "description": "tekstilkunstner"
            }
        ],
        "others": [],
        "relations": [
            {
                "type": "Datter av",
                "external_id": "person_8736ab102263",
                "birth_date": "",
                "death_date": "",
                "firstname": "Ingrid",
                "lastname": "Bjørneng",
                "professions": []
            },
            {
                "type": "Gift med",
                "external_id": "person_8736ab102264",
                "birth_date": "",
                "death_date": "",
                "firstname": "Harald Wilhelm",
                "lastname": "Foss",
                "professions": []
            },
            {
                "type": "Datter av",
                "external_id": "person_8736ab102262",
                "birth_date": "",
                "death_date": "",
                "firstname": "Kaare",
                "lastname": "Foss",
                "professions": []
            }
        ],
        "residences": [
            {
                "order": "0",
                "description": "Gvarv"
            }
        ],
        "educations": [
            {
                "comment": "Statens lærerskole i forming, Oslo 1970",
                "order": "2"
            },
            {
                "comment": "Konstindustriskolan, Göteborg 1969",
                "order": "1"
            },
            {
                "comment": "Bergen kunsthåndverkskole 1965–68",
                "order": "0"
            }
        ],
        "travels": [],
        "memberships": [
            {
                "order": "0",
                "description": "Medlem av Unge Kunstneres Samfund"
            }
        ],
        "awards": [],
        "public_productions": [
            {
                "from_date": "",
                "order": "0",
                "to_date": "",
                "description": "F. har utført tekstilarbeid til Stord Bartz Industrien"
            },
            {
                "from_date": "",
                "order": "1",
                "to_date": "",
                "description": "Akkerhaugen Turisthotell"
            },
            {
                "from_date": "",
                "order": "2",
                "to_date": "",
                "description": "Telemark fylke"
            }
        ],
        "performed_productions": [],
        "illustrations": [],
        "exhibitions": [
            {
                "category": "Kollektiv",
                "from_date": "1979",
                "order": "0",
                "to_date": "",
                "title": "Sørlandsutstillingen"
            },
            {
                "category": "Kollektiv",
                "from_date": "",
                "order": "6",
                "to_date": "",
                "title": "Telemark vårutstilling"
            },
            {
                "category": "Kollektiv",
                "exhibition_organizer": "Vestlandske Kunstindustrimuseum, Bergen",
                "from_date": "1973",
                "order": "4",
                "to_date": ""
            },
            {
                "category": "Kollektiv",
                "from_date": "",
                "order": "5",
                "to_date": "",
                "title": "Seljordutstillingen"
            },
            {
                "category": "Kollektiv",
                "exhibition_organizer": "Haugesund Kunstforening",
                "from_date": "1975",
                "order": "3",
                "to_date": ""
            },
            {
                "category": "Kollektiv",
                "exhibition_organizer": "Ibsenhuset, Skien",
                "from_date": "1973",
                "order": "1",
                "to_date": ""
            },
            {
                "category": "Kollektiv",
                "exhibition_organizer": "Brevik",
                "from_date": "1974",
                "order": "2",
                "to_date": "",
                "title": "Gruppe 9"
            }
        ],
        "portraits": [],
        "authorships": [],
        "publishings": [],
        "archives": [],
        "radio_and_tv_programs": []
    },
    "title": "Mari Foss",
    "url": "https://nkl.snl.no/Mari_Foss",
    "subject_url": "http://snl.no/.taxonomy/3405",
    "subject_title": "Norsk kunstnerleksikon",
    "xhtml_body": "<div></div>",
    "created_at": "2013-07-03T23:09:27.756+02:00",
    "changed_at": "2024-06-18T23:26:15.277+02:00",
    "license_name": "begrenset",
    "metadata_license_name": "fri",
    "metadata": {
        "gender": "k",
        "same_as": "[\"http://data.nasjonalmuseet.no/resource/person_8736ab1104\",\"https://digitaltmuseum.no/4ae85d93-1969-4674-897a-798947a1d3da\",\"http://kulturnav.org/4ae85d93-1969-4674-897a-798947a1d3da\"]",
        "lastname": "Foss",
        "firstname": "Mari",
        "birth_date": "16.7.1946",
        "birthplace": "Østre Gausdal",
        "external_id": "person_8736ab1104",
        "kulturnav_id": "4ae85d93-1969-4674-897a-798947a1d3da",
        "alternative_names": "Foss, Mari Gudrun"
    },
    "authors": [
        {
            "full_name": " Norsk kunstnerleksikon"
        }
    ],
    "images": [],
    "professions": [
        {
            "description": "tekstilkunstner"
        }
    ]
}