{
    "id": 431203,
    "headword": "Per Palle Storm",
    "custom_metadata_json": {
        "professions": [
            {
                "description": "tegner"
            },
            {
                "description": "billedhugger"
            },
            {
                "description": "grafiker"
            }
        ],
        "others": [],
        "relations": [
            {
                "from_date": "1948",
                "type": "Gift med",
                "external_id": "person_8736ab107265",
                "birth_date": "1903",
                "death_date": "",
                "firstname": "Ingeborg",
                "lastname": "Dal",
                "professions": []
            },
            {
                "type": "Sønn av",
                "external_id": "person_8736ab107264",
                "birth_date": "",
                "death_date": "",
                "firstname": "Ellen",
                "lastname": "von Müllen",
                "professions": []
            },
            {
                "type": "Sønn av",
                "external_id": "person_8736ab107263",
                "birth_date": "",
                "death_date": "",
                "firstname": "Hans Peter",
                "lastname": "Storm",
                "professions": []
            }
        ],
        "residences": [],
        "educations": [
            {
                "comment": "Elev av Bartholomé Tasso og Urbici Solér, Buenos Aires 1927–29",
                "order": "0"
            },
            {
                "comment": "Statens Kunstakademi, Oslo under Wilhelm Rasmussen 1930–33",
                "order": "1"
            }
        ],
        "travels": [
            {
                "order": "6",
                "description": "Senere studiereiser bl.a. til Tyskland, Danmark, Italia, Belgia, Nederland, Sverige"
            },
            {
                "order": "0",
                "description": "Oslo bys kulturstipend 1937"
            },
            {
                "order": "2",
                "description": "Bosatt i Buenos Aires ca. 1913–30"
            },
            {
                "order": "4",
                "description": "Bosatt i Norge fra 1930"
            },
            {
                "order": "1",
                "description": "Conrad Mohrs stipend 1933"
            },
            {
                "order": "7",
                "description": "Libanon, Tyrkia, Hellas og Italia 1957–58"
            },
            {
                "order": "10",
                "description": "Sicilia 1974"
            },
            {
                "order": "9",
                "description": "Liberia 1969"
            },
            {
                "order": "8",
                "description": "Nordland 1965"
            },
            {
                "order": "3",
                "description": "Reiste til Europa, besøkte Bologna, Venezia, Firenze og Berlin 1930"
            },
            {
                "order": "5",
                "description": "Studieopphold i Paris 6 mndr. 1933"
            },
            {
                "order": "11",
                "description": "Hellas 1977"
            }
        ],
        "memberships": [
            {
                "order": "2",
                "description": "Stemmerett Bildende Kunstneres Styre"
            },
            {
                "order": "1",
                "description": "Professor Statens Kunstakademi, Oslo 1947-80"
            },
            {
                "order": "0",
                "description": "Lærer Det illegale Akademi 1943-45, undervisning til 1947"
            },
            {
                "order": "5",
                "description": "Jurymedlem en rekke konkurranser bl.a. Hvalfangstmonument i Sandefjord 1953, monument over Oscar Mathiesen, Oslo 1957, monument over Sonja Henie, Oslo 1975, monument over falne, Bærum"
            },
            {
                "order": "3",
                "description": "Medlem Norsk Billedhuggerforening, viseformann 1946-49"
            },
            {
                "order": "4",
                "description": "Direksjonsmedlem Kunstnernes Hus, Oslo 1946-57"
            }
        ],
        "awards": [
            {
                "order": "9",
                "description": "Kongens fortjenstmedalje i gull"
            },
            {
                "order": "8",
                "description": "1. premie i engere konkurranse Christian Michelsen-monument, Stortinget (1980)"
            },
            {
                "order": "4",
                "description": "1. premie i konkurranse Thorleif Haug-monumentet, Drammen (1939)"
            },
            {
                "order": "2",
                "description": "Innkjøp i konkurranse utsmykkingen av Oslo rådhus 1938"
            },
            {
                "order": "7",
                "description": "3. premie i konkurranse Haakon 7-monument, Oslo sammen med A. Vigeland (1967)"
            },
            {
                "order": "11",
                "description": "Grand Commander of the Star of Africa 1969"
            },
            {
                "order": "5",
                "description": "1. premie i konkurranse minnesmerke over Sarpsborg-distriktets falne, Sarpsborg (1946)"
            },
            {
                "order": "10",
                "description": "R. Dannebrog-Orden"
            },
            {
                "order": "1",
                "description": "Premie i konkurranse Holberg-monumentet, Oslo (1938)"
            },
            {
                "order": "12",
                "description": "R1St. Olavs Orden 1980"
            },
            {
                "order": "3",
                "description": "Delt 1. premie i konkurranse Arbeiderbevegelsens monument, Youngstorget, Oslo (2 av 4 premierte utkast)"
            },
            {
                "order": "6",
                "description": "3. premie i konkurranse Christian Krohg-monument, Oslo (1950)"
            },
            {
                "order": "0",
                "description": "3. premie i konkurranse utsmykking av Ankerbrua, Oslo (1933)"
            }
        ],
        "public_productions": [
            {
                "from_date": "",
                "order": "71",
                "to_date": "",
                "description": "Selskapet Kunst på Arbeidsplassen"
            },
            {
                "from_date": "",
                "order": "75",
                "to_date": "",
                "description": "Seljord og Sarpsborg kunstforeninger"
            },
            {
                "from_date": "",
                "order": "61",
                "to_date": "",
                "description": "Olav den Hellige, Lyngdal (bronse avduket 1983)"
            },
            {
                "from_date": "",
                "order": "32",
                "to_date": "",
                "description": "Krigsmonument, Riis kirke, Oslo (bronse avduket 1952)"
            },
            {
                "from_date": "",
                "order": "24",
                "to_date": "",
                "description": "Familien,Wiels plass, Halden (granitt 1943/44)"
            },
            {
                "from_date": "",
                "order": "37",
                "to_date": "",
                "description": "Byste, Theodor Kittelsen, Bjørnsborgparken, Kragerø (bronse 1958)"
            },
            {
                "from_date": "",
                "order": "57",
                "to_date": "",
                "description": "Prost Hans Peter Schnitler Krag, Fjellbygda kirke, Røyrvik (bronse ca. 1978)"
            },
            {
                "from_date": "",
                "order": "42",
                "to_date": "",
                "description": "Byste, Professor H. P. L'Orange, Det Norske Institutt i Roma (bronse 1960)"
            },
            {
                "from_date": "",
                "order": "51",
                "to_date": "",
                "description": "Byste, Professor Francis Bull, Nordisk Institutt, Universitetet i Oslo (bronse 1968)"
            },
            {
                "from_date": "",
                "order": "76",
                "to_date": "",
                "description": "Halden, Drammen, Moss, Stavanger, Porsgrunn, Horten, Kristiansand, Tromsø og Kragerø kommuner"
            },
            {
                "from_date": "",
                "order": "47",
                "to_date": "",
                "description": "Norsk gjetebukk, Bybroen ved Kongsgården, Halden (bronse 1965)"
            },
            {
                "from_date": "",
                "order": "41",
                "to_date": "",
                "description": "Mann som drikker, Kronprinsesse Märthas plass, Oslo (bronse 1960)"
            },
            {
                "from_date": "",
                "order": "21",
                "to_date": "",
                "description": "Sammenkrøket, Kristiansand (bronse 1938/45)"
            },
            {
                "from_date": "",
                "order": "27",
                "to_date": "",
                "description": "Krigsminnesmerke, Akershus festning, Oslo (granitt 1949)"
            },
            {
                "from_date": "",
                "order": "67",
                "to_date": "",
                "description": "Arkivmuseet, Lund"
            },
            {
                "from_date": "",
                "order": "33",
                "to_date": "",
                "description": "Byster, Hr. og Fru Fearnley, Herredshuset, Hole (bronse ca. 1953)"
            },
            {
                "from_date": "",
                "order": "38",
                "to_date": "",
                "description": "Drikkende gutt, Horten gymnas (bronse 1958)"
            },
            {
                "from_date": "",
                "order": "62",
                "to_date": "",
                "description": "Nasjonalgalleriet, Oslo"
            },
            {
                "from_date": "",
                "order": "52",
                "to_date": "",
                "description": "Martin Tranmæl, LO-skolen i Sørmarka, Oppegård (bronse avduket 1969)"
            },
            {
                "from_date": "",
                "order": "58",
                "to_date": "",
                "description": "To hunder, Ullensaker sykehjem (bronse avduket 1979)"
            },
            {
                "from_date": "",
                "order": "43",
                "to_date": "",
                "description": "Byste, Rådmann Arne Magnussen, Kransen, Moss (bronse 1960)"
            },
            {
                "from_date": "",
                "order": "25",
                "to_date": "",
                "description": "Monument over falne, Sarpsborg (bronse 1948)"
            },
            {
                "from_date": "",
                "order": "72",
                "to_date": "",
                "description": "Norsk Kulturråd"
            },
            {
                "from_date": "",
                "order": "48",
                "to_date": "",
                "description": "Ung løve, Norges Bank, Oslo (bronse 1965/66)"
            },
            {
                "from_date": "",
                "order": "53",
                "to_date": "",
                "description": "Byste, Professor dr.med. Bjarne Dahl, Rikshospitalet, Oslo (bronse avduket 1970)"
            },
            {
                "from_date": "",
                "order": "68",
                "to_date": "",
                "description": "Göteborgs Konstmuseum"
            },
            {
                "from_date": "",
                "order": "28",
                "to_date": "",
                "description": "Kong Haakon, Torget i Kristiansand (bronse 1950/51)"
            },
            {
                "from_date": "",
                "order": "73",
                "to_date": "",
                "description": "Riksgalleriet"
            },
            {
                "from_date": "",
                "order": "44",
                "to_date": "",
                "description": "Byste, skuespillerinne Tore Segelcke, Nationaltheatret, Oslo (bronse 1961)"
            },
            {
                "from_date": "",
                "order": "69",
                "to_date": "",
                "description": "Det Kgl. Slott"
            },
            {
                "from_date": "",
                "order": "59",
                "to_date": "",
                "description": "Byste, Christian Michelsen, Eidsvolls plass, Oslo (bronse 1980)"
            },
            {
                "from_date": "",
                "order": "63",
                "to_date": "",
                "description": "Bergen Billedgalleri"
            },
            {
                "from_date": "",
                "order": "34",
                "to_date": "",
                "description": "Minnesmerke over de henrettede i Trandumskogen, Ullensaker (granitt ca. 1953)"
            },
            {
                "from_date": "",
                "order": "23",
                "to_date": "",
                "description": "Fortuna, Holmenvn. 19, Oslo (bronse ca. 1940)"
            },
            {
                "from_date": "",
                "order": "49",
                "to_date": "",
                "description": "Kong Haakon, Rådhusparken, Tromsø (bronse, 1967-69)"
            },
            {
                "from_date": "",
                "order": "54",
                "to_date": "",
                "description": "Ung kvinne, Svømmehallen i Tønsberg (bronse 1971)"
            },
            {
                "from_date": "",
                "order": "39",
                "to_date": "",
                "description": "Hane, Bekkefaret, Oslo (bronse ca. 1958)"
            },
            {
                "from_date": "",
                "order": "29",
                "to_date": "",
                "description": "Rådhusskulpturene, Oslo (bronse): Håndlangeren (1949/50), Elektrikeren (1950), Steinhoggeren (1950), Tømmermannen (ca. 1951), Mureren (1951), Steinbryteren (stein, jord og sementarbeideren) (1960)"
            },
            {
                "from_date": "",
                "order": "74",
                "to_date": "",
                "description": "Norske Museers Landsforbund"
            },
            {
                "from_date": "",
                "order": "45",
                "to_date": "",
                "description": "Byste, Forlagsbokhandler Jørgen Wright Cappelen, Cappelen forlag, Oslo (bronse ca. 1961)"
            },
            {
                "from_date": "",
                "order": "70",
                "to_date": "",
                "description": "Oslo kommunes kunstsamlinger"
            },
            {
                "from_date": "",
                "order": "26",
                "to_date": "",
                "description": "Bacchus og Venus, grupper utført til M/S Stella Polaris (bronse 1948)"
            },
            {
                "from_date": "",
                "order": "31",
                "to_date": "",
                "description": "Byste, Direktør William Henry Sneath, Sauda (bronse avduket 1951)"
            },
            {
                "from_date": "",
                "order": "60",
                "to_date": "",
                "description": "Byste, Rolf Hofmo, Norges idrettshøgskole, Oslo (bronse avduket 1981)"
            },
            {
                "from_date": "",
                "order": "35",
                "to_date": "",
                "description": "Bergmannen, Løkken Verk, Orkla (bronse 1955)"
            },
            {
                "from_date": "",
                "order": "36",
                "to_date": "",
                "description": "Arbeiderbevegelsens pionerer, Youngstorget, Oslo (bronse 1948-55, avduket 1958) omarbeidet etter 1. premie i konkurranse 1937"
            },
            {
                "from_date": "",
                "order": "64",
                "to_date": "",
                "description": "Trøndelag Kunstgalleri"
            },
            {
                "from_date": "",
                "order": "50",
                "to_date": "",
                "description": "Byste, Sigbjørn Obstfelder, Norges Tekniske Høyskole, Trondheim (bronse 1968)"
            },
            {
                "from_date": "",
                "order": "22",
                "to_date": "",
                "description": "Monument over Thorleif Haug, Drammen (bronse 1941)"
            },
            {
                "from_date": "",
                "order": "40",
                "to_date": "",
                "description": "Ridende jockey, Norges idrettshøgskole, Oslo (bronse 1958)"
            },
            {
                "from_date": "",
                "order": "55",
                "to_date": "",
                "description": "Byste, Ole Mørk Sandvig, Universitetsbiblioteket, Oslo (bronse 1973)"
            },
            {
                "from_date": "",
                "order": "56",
                "to_date": "",
                "description": "Bauta, Gunvald Tomstad, Flekkefjord kirke (bronserelieff på granittsokkel 1977)"
            },
            {
                "from_date": "",
                "order": "30",
                "to_date": "",
                "description": "Byste, Statsråd Sven Oftedal, Sven Oftedals plass, Stavanger (bronse 1950)"
            },
            {
                "from_date": "",
                "order": "66",
                "to_date": "",
                "description": "Statens Museum for Kunst, København"
            },
            {
                "from_date": "",
                "order": "65",
                "to_date": "",
                "description": "Haugesund Billedgalleri"
            },
            {
                "from_date": "",
                "order": "46",
                "to_date": "",
                "description": "Byste, Professor dr.med. Johan Cappelen Frimann-Dahl, Ullevål sykehus, Oslo (bronse 1962)"
            }
        ],
        "performed_productions": [],
        "illustrations": [
            {
                "from_date": "",
                "order": "81",
                "to_date": "",
                "description": "K. F. Brøgger: Pengefyrsten, Oslo 1943"
            },
            {
                "from_date": "",
                "order": "82",
                "to_date": "",
                "description": "Benvenuto Cellini: Mitt liv, Oslo 1946"
            }
        ],
        "exhibitions": [
            {
                "category": "Kollektiv",
                "exhibition_organizer": "Helsinki",
                "from_date": "1950",
                "order": "36",
                "to_date": "",
                "title": "Nordisk konst"
            },
            {
                "category": "Kollektiv",
                "exhibition_organizer": "Nasjonalgalleriet, Oslo",
                "from_date": "1984",
                "order": "63",
                "to_date": "",
                "title": "Kunstakademiets professorer gjennem 75 år"
            },
            {
                "category": "Kollektiv",
                "from_date": "1940",
                "order": "22",
                "to_date": "",
                "title": "Nasjonalgalleriets retrospektive utstilling over norsk kunst"
            },
            {
                "category": "Separat",
                "exhibition_organizer": "Kunstnerforbundet, Oslo",
                "from_date": "1972",
                "order": "2",
                "to_date": ""
            },
            {
                "category": "Kollektiv",
                "exhibition_organizer": "Kunstnernes Hus, Oslo",
                "from_date": "1941",
                "order": "26",
                "to_date": "",
                "title": "Yngre norsk skulptur"
            },
            {
                "category": "Kollektiv",
                "exhibition_organizer": "Helsinki",
                "from_date": "1956",
                "order": "42",
                "to_date": "",
                "title": "Norsk nutidskonst"
            },
            {
                "category": "Kollektiv",
                "from_date": "1974",
                "order": "16",
                "to_date": "1976",
                "title": "Høstutstillingen"
            },
            {
                "category": "Kollektiv",
                "exhibition_organizer": "Kunstnerforbundet, Oslo",
                "from_date": "1975",
                "order": "59",
                "to_date": ""
            },
            {
                "category": "Kollektiv",
                "exhibition_organizer": "Kunstnerforbundet, Oslo",
                "from_date": "1961",
                "order": "49",
                "to_date": "",
                "title": "43 kunstnere"
            },
            {
                "category": "Kollektiv",
                "from_date": "1959",
                "order": "12",
                "to_date": "",
                "title": "Høstutstillingen"
            },
            {
                "category": "Kollektiv",
                "exhibition_organizer": "Nasjonalgalleriet, Oslo",
                "from_date": "1958",
                "order": "39",
                "to_date": ""
            },
            {
                "category": "Kollektiv",
                "exhibition_organizer": "København",
                "from_date": "1947",
                "order": "31",
                "to_date": "",
                "title": "Den Officielle Norske Kunstudst."
            },
            {
                "category": "Kollektiv",
                "exhibition_organizer": "Göteborg",
                "from_date": "1939",
                "order": "21",
                "to_date": "",
                "title": "Nordisk konst"
            },
            {
                "category": "Kollektiv",
                "exhibition_organizer": "Odense",
                "from_date": "1959",
                "order": "47",
                "to_date": "",
                "title": "Nordisk kunst gjennom 10 år, 1949–59"
            },
            {
                "category": "Kollektiv",
                "exhibition_organizer": "København",
                "from_date": "1966",
                "order": "53",
                "to_date": "",
                "title": "Nordisk nutidskunst"
            },
            {
                "category": "Kollektiv",
                "exhibition_organizer": "Selskapet Kunst på Arbeidsplassen",
                "from_date": "1973",
                "order": "57",
                "to_date": "",
                "title": "Nordisk skulpturutst."
            },
            {
                "category": "Separat",
                "exhibition_organizer": "Seljord Kunstforening",
                "from_date": "1975",
                "order": "7",
                "to_date": ""
            },
            {
                "category": "Kollektiv",
                "exhibition_organizer": "Kunstnerforbundet, Oslo",
                "from_date": "1981",
                "order": "62",
                "to_date": "",
                "title": "Profiler-81"
            },
            {
                "category": "Kollektiv",
                "exhibition_organizer": "Kunstnernes Hus, Oslo",
                "from_date": "1950",
                "order": "35",
                "to_date": "",
                "title": "Norsk Billedhuggerforening-utst."
            },
            {
                "category": "Separat",
                "exhibition_organizer": "Kunstnerforbundet, Oslo",
                "from_date": "1977",
                "order": "3",
                "to_date": ""
            },
            {
                "category": "Kollektiv",
                "from_date": "1971",
                "order": "15",
                "to_date": "",
                "title": "Høstutstillingen"
            },
            {
                "category": "Kollektiv",
                "exhibition_organizer": "Kunstnernes Hus, Oslo",
                "from_date": "1969",
                "order": "25",
                "to_date": "",
                "title": "sommerutst."
            },
            {
                "category": "Kollektiv",
                "exhibition_organizer": "Göteborg",
                "from_date": "1957",
                "order": "43",
                "to_date": "",
                "title": "Nordisk Kunstforbunds utstillinger"
            },
            {
                "category": "Kollektiv",
                "from_date": "1945",
                "order": "10",
                "to_date": "",
                "title": "Høstutstillingen"
            },
            {
                "category": "Kollektiv",
                "exhibition_organizer": "Kunstnernes Hus, Oslo",
                "from_date": "1957",
                "order": "44",
                "to_date": "",
                "title": "Unge Kunstneres Samfunn jub.utst."
            },
            {
                "category": "Kollektiv",
                "from_date": "1953",
                "order": "11",
                "to_date": "",
                "title": "Høstutstillingen"
            },
            {
                "category": "Kollektiv",
                "exhibition_organizer": "Stockholm",
                "from_date": "1946",
                "order": "30",
                "to_date": "1947",
                "title": "Nordisk konst"
            },
            {
                "category": "Kollektiv",
                "exhibition_organizer": "Kunstnernes Hus, Oslo",
                "from_date": "1938",
                "order": "20",
                "to_date": "",
                "title": "Dansk-norsk billedhuggersammenslutning"
            },
            {
                "category": "Kollektiv",
                "exhibition_organizer": "Kunstnerforbundet, Oslo",
                "from_date": "1961",
                "order": "48",
                "to_date": "",
                "title": "jub.utst"
            },
            {
                "category": "Kollektiv",
                "exhibition_organizer": "Nasjonalgalleriet, Oslo",
                "from_date": "1966",
                "order": "52",
                "to_date": "",
                "title": "Norsk tegnekunst"
            },
            {
                "category": "Separat",
                "exhibition_organizer": "Festspillene i Nord-Norge, Harstad",
                "from_date": "1968",
                "order": "6",
                "to_date": ""
            },
            {
                "category": "Kollektiv",
                "exhibition_organizer": "Gall. Norske Grafikere",
                "from_date": "1974",
                "order": "58",
                "to_date": "",
                "title": "Billedhuggere som grafikere og grafikere som billedhuggere"
            },
            {
                "category": "Kollektiv",
                "from_date": "1933",
                "order": "9",
                "to_date": "1935",
                "title": "Høstutstillingen"
            },
            {
                "category": "Kollektiv",
                "from_date": "1953",
                "order": "38",
                "to_date": "",
                "title": "2. Bienal São Paulo"
            },
            {
                "category": "Separat",
                "exhibition_organizer": "Nasjonalgalleriet, Oslo",
                "from_date": "1953",
                "order": "4",
                "to_date": ""
            },
            {
                "category": "Kollektiv",
                "exhibition_organizer": "Kunstnernes Hus, Oslo",
                "from_date": "1967",
                "order": "54",
                "to_date": "",
                "title": "Utkast til Haakon 7-monument"
            },
            {
                "category": "Separat",
                "exhibition_organizer": "Kunstnerforbundet, Oslo",
                "from_date": "1941",
                "order": "0",
                "to_date": ""
            },
            {
                "category": "Kollektiv",
                "exhibition_organizer": "Kunstnernes Hus, Oslo",
                "from_date": "1941",
                "order": "24",
                "to_date": "",
                "title": "sommerutst."
            },
            {
                "category": "Kollektiv",
                "exhibition_organizer": "Kunstnernes Hus, Oslo",
                "from_date": "1980",
                "order": "61",
                "to_date": "",
                "title": "Kunstnernes Hus, Oslo 1930-1980, jub.utst."
            },
            {
                "category": "Kollektiv",
                "from_date": "1937",
                "order": "18",
                "to_date": "",
                "title": "Verdensutstillingen i Paris"
            },
            {
                "category": "Kollektiv",
                "exhibition_organizer": "København",
                "from_date": "1949",
                "order": "34",
                "to_date": "",
                "title": "Nordisk Kunstudst."
            },
            {
                "category": "Kollektiv",
                "from_date": "1967",
                "order": "14",
                "to_date": "1969",
                "title": "Høstutstillingen"
            },
            {
                "category": "Kollektiv",
                "exhibition_organizer": "Kunstnernes Hus, Oslo",
                "from_date": "1957",
                "order": "45",
                "to_date": "",
                "title": "Auksjon"
            },
            {
                "category": "Kollektiv",
                "exhibition_organizer": "Kunstnerforbundet, Oslo",
                "from_date": "1955",
                "order": "41",
                "to_date": ""
            },
            {
                "category": "Kollektiv",
                "exhibition_organizer": "Kunstnernes Hus, Oslo",
                "from_date": "1946",
                "order": "28",
                "to_date": "",
                "title": "Unge Kunstneres Samfunn jub.utst."
            },
            {
                "category": "Kollektiv",
                "exhibition_organizer": "Unge Kunstneres Samfunn",
                "from_date": "1964",
                "order": "51",
                "to_date": ""
            },
            {
                "category": "Kollektiv",
                "exhibition_organizer": "Nasjonalgalleriet, Oslo",
                "from_date": "1969",
                "order": "55",
                "to_date": "",
                "title": "Statens Kunstakademi 60 år"
            },
            {
                "category": "Kollektiv",
                "exhibition_organizer": "Kunstnernes Hus, Oslo",
                "from_date": "1937",
                "order": "19",
                "to_date": "",
                "title": "Konkurranseutst. til Arbeiderbevegelsens monument"
            },
            {
                "category": "Kollektiv",
                "exhibition_organizer": "Stockholm",
                "from_date": "1951",
                "order": "37",
                "to_date": "",
                "title": "Norsk nutidskonst"
            },
            {
                "category": "Separat",
                "exhibition_organizer": "Trondheim Kunstforening",
                "from_date": "1954",
                "order": "5",
                "to_date": ""
            },
            {
                "category": "Kollektiv",
                "exhibition_organizer": "Nasjonalgalleriet, Oslo",
                "from_date": "1941",
                "order": "23",
                "to_date": "",
                "title": "Billedhuggeres tegninger"
            },
            {
                "category": "Kollektiv",
                "exhibition_organizer": "Kunstnernes Hus, Oslo",
                "from_date": "1934",
                "order": "17",
                "to_date": "",
                "title": "Norsk skulptur"
            },
            {
                "category": "Separat",
                "exhibition_organizer": "Kunstnerforbundet, Oslo",
                "from_date": "1960",
                "order": "1",
                "to_date": ""
            },
            {
                "category": "Kollektiv",
                "exhibition_organizer": "Kunstnernes Hus, Oslo",
                "from_date": "1976",
                "order": "60",
                "to_date": "",
                "title": "Norsk tegnekunst i 60 år"
            },
            {
                "category": "Kollektiv",
                "exhibition_organizer": "Oslo Kunstforening",
                "from_date": "1948",
                "order": "33",
                "to_date": "",
                "title": "Norske tegnere"
            },
            {
                "category": "Kollektiv",
                "exhibition_organizer": "Kunstnernes Hus, Oslo",
                "from_date": "1946",
                "order": "29",
                "to_date": "",
                "title": "Nordisk Kunstforbunds utstillinger utst."
            },
            {
                "category": "Kollektiv",
                "exhibition_organizer": "Kunstnernes Hus, Oslo",
                "from_date": "1947",
                "order": "32",
                "to_date": "",
                "title": "Professorkonkurransen"
            },
            {
                "category": "Kollektiv",
                "exhibition_organizer": "Kunstnerforbundet, Oslo",
                "from_date": "1953",
                "order": "40",
                "to_date": "",
                "title": "Svart og hvitt i dag"
            },
            {
                "category": "Kollektiv",
                "from_date": "1961",
                "order": "13",
                "to_date": "1965",
                "title": "Høstutstillingen"
            },
            {
                "category": "Kollektiv",
                "exhibition_organizer": "Kunstnerforbundet, Oslo",
                "from_date": "1959",
                "order": "46",
                "to_date": "",
                "title": "Vårutst."
            },
            {
                "category": "Separat",
                "exhibition_organizer": "Gall. Tanum",
                "from_date": "1976",
                "order": "8",
                "to_date": ""
            },
            {
                "category": "Kollektiv",
                "exhibition_organizer": "Kunstnerforbundet, Oslo",
                "from_date": "1942",
                "order": "27",
                "to_date": "",
                "title": "Hageskulpturutst."
            },
            {
                "category": "Kollektiv",
                "exhibition_organizer": "Trondheim Kunstforening",
                "from_date": "1973",
                "order": "56",
                "to_date": "",
                "title": "sommerutst."
            },
            {
                "category": "Kollektiv",
                "exhibition_organizer": "Kunstnernes Hus, Oslo",
                "from_date": "1962",
                "order": "50",
                "to_date": "",
                "title": "Vår skulptur i dag"
            }
        ],
        "portraits": [
            {
                "from_date": "",
                "order": "80",
                "to_date": "",
                "description": "Tegning utført av Ulf Aas gjengitt i Aftenposten 25.4. 1980"
            },
            {
                "from_date": "",
                "order": "79",
                "to_date": "",
                "description": "Tegning utført av Pedro (Salo Grenning) gjengitt i Verdens Gang 9.3. 1957"
            },
            {
                "from_date": "",
                "order": "78",
                "to_date": "",
                "description": "Selvportrett, byste (ubrent leire)"
            },
            {
                "from_date": "",
                "order": "77",
                "to_date": "",
                "description": "Selvportrett, tegning gjengitt bl.a. i Aftenposten 8.3. 1947"
            }
        ],
        "authorships": [],
        "publishings": [
            {
                "from_date": "1983",
                "order": "75",
                "reference": "s. 281",
                "to_date": "",
                "description": "Kunst og Kultur",
                "authors": [],
                "comments": [],
                "archives": []
            },
            {
                "from_date": "1969",
                "order": "27",
                "reference": "s. 24, 26–29, 32, 73",
                "to_date": "",
                "description": "Statens Kunstakademi 60 år",
                "place": "Oslo",
                "authors": [
                    "Thue, O."
                ],
                "comments": [
                    "katalog Nasjonalgalleriet Oslo"
                ],
                "archives": []
            },
            {
                "from_date": "1981",
                "order": "37",
                "reference": "bd. 11, s. 203 (ill.)",
                "to_date": "",
                "description": "Aschehoug og Gyldendals store norske leksikon",
                "place": "Olso",
                "authors": [],
                "comments": [],
                "archives": []
            },
            {
                "from_date": "1971",
                "order": "65",
                "reference": "s. 132, 248",
                "to_date": "",
                "description": "Kunst og Kultur register 1910-67",
                "place": "Oslo",
                "authors": [],
                "comments": [],
                "archives": []
            },
            {
                "from_date": "",
                "optional_reference": "(u.å.), s. 16",
                "order": "4",
                "to_date": "",
                "description": "Kunsten i Oslo Rådhus",
                "place": "Oslo",
                "authors": [
                    "Rom, P. (red.)"
                ],
                "comments": [],
                "archives": []
            },
            {
                "from_date": "1980-12-01",
                "order": "131",
                "reference": "(ill.)",
                "to_date": "",
                "description": "i Aftenposten",
                "authors": [
                    "Johnsrud, E. H."
                ],
                "comments": [],
                "archives": []
            },
            {
                "from_date": "1969",
                "order": "66",
                "reference": "s. 127",
                "to_date": "",
                "description": "Kunst og Kultur",
                "authors": [],
                "comments": [],
                "archives": []
            },
            {
                "from_date": "1972-05-06",
                "order": "111",
                "reference": "(ill.)",
                "to_date": "",
                "description": "i Dagbladet",
                "authors": [
                    "Harr, K. E."
                ],
                "comments": [],
                "archives": []
            },
            {
                "from_date": "1966-09-09",
                "order": "104",
                "reference": "(ill.)",
                "to_date": "",
                "description": "i Politiken",
                "place": "København",
                "authors": [
                    "Lübecker, P."
                ],
                "comments": [],
                "archives": []
            },
            {
                "from_date": "1963",
                "order": "57",
                "reference": "hefte 65 s. 31",
                "to_date": "",
                "description": "Kunsten idag",
                "authors": [],
                "comments": [],
                "archives": []
            },
            {
                "from_date": "1947-02-22",
                "order": "85",
                "to_date": "",
                "description": "Dagbladet",
                "authors": [],
                "comments": [],
                "archives": []
            },
            {
                "from_date": "1949",
                "order": "47",
                "reference": "nr. 9 s. 12, 67 (ill.)",
                "to_date": "",
                "description": "Bonytt",
                "authors": [],
                "comments": [],
                "archives": []
            },
            {
                "from_date": "1960-10-17",
                "order": "95",
                "to_date": "",
                "description": "i Verdens Gang",
                "authors": [
                    "Michelet, J. F."
                ],
                "comments": [],
                "archives": []
            },
            {
                "from_date": "1956",
                "order": "14",
                "reference": "register, s. 279",
                "to_date": "",
                "description": "Norske portretter, Forfattere",
                "place": "Oslo",
                "authors": [],
                "comments": [],
                "archives": []
            },
            {
                "from_date": "1980-04-17",
                "order": "125",
                "reference": "(ill.)",
                "to_date": "",
                "description": "i Verdens Gang",
                "authors": [
                    "Næss, A."
                ],
                "comments": [],
                "archives": []
            },
            {
                "from_date": "1937-08-18",
                "order": "76",
                "to_date": "",
                "description": "Arbeiderbladet",
                "authors": [],
                "comments": [],
                "archives": []
            },
            {
                "from_date": "1969",
                "order": "26",
                "reference": "register s. 322 (ill.)",
                "to_date": "",
                "description": "Norsk skulptur i femti år",
                "place": "Oslo",
                "authors": [
                    "Parmann, Ø."
                ],
                "comments": [],
                "archives": []
            },
            {
                "from_date": "1948",
                "order": "3",
                "reference": "s. 109, 115–16 (ill.)",
                "to_date": "",
                "description": "i Vår tids kunst og diktning i Skandinavia",
                "place": "Oslo",
                "authors": [
                    "Finne, H."
                ],
                "comments": [],
                "archives": []
            },
            {
                "from_date": "1976-01-27",
                "order": "118",
                "to_date": "",
                "description": "i Norges Handels og Sjøfartstidende",
                "authors": [
                    "Durbin, A."
                ],
                "comments": [],
                "archives": []
            },
            {
                "from_date": "1980",
                "order": "36",
                "reference": "s. 8",
                "to_date": "",
                "description": "Arnold Haukeland",
                "place": "Oslo",
                "authors": [
                    "Dæhlin, E."
                ],
                "comments": [],
                "archives": []
            },
            {
                "from_date": "1970",
                "order": "67",
                "reference": "s. 67, 194",
                "to_date": "",
                "description": "Kunst og Kultur",
                "authors": [],
                "comments": [],
                "archives": []
            },
            {
                "from_date": "1980-09-02",
                "order": "130",
                "to_date": "",
                "description": "Dagen",
                "authors": [],
                "comments": [],
                "archives": []
            },
            {
                "from_date": "1962",
                "order": "56",
                "reference": "hefte 62 s. 5",
                "to_date": "",
                "description": "Kunsten idag",
                "authors": [],
                "comments": [],
                "archives": []
            },
            {
                "from_date": "1966-09-23",
                "order": "105",
                "to_date": "",
                "description": "i Aktuelt",
                "place": "København",
                "authors": [
                    "Wilmann, P."
                ],
                "comments": [],
                "archives": []
            },
            {
                "from_date": "1947-02-13",
                "order": "86",
                "to_date": "",
                "description": "Morgenbladet",
                "authors": [],
                "comments": [],
                "archives": []
            },
            {
                "from_date": "1970-12-02",
                "order": "110",
                "to_date": "",
                "description": "i Morgenposten",
                "authors": [
                    "Durbin, A."
                ],
                "comments": [],
                "archives": []
            },
            {
                "from_date": "1980-01-26",
                "order": "124",
                "reference": "(ill.)",
                "to_date": "",
                "description": "Fædrelandsvennen",
                "authors": [],
                "comments": [],
                "archives": []
            },
            {
                "from_date": "1960-10-18",
                "order": "96",
                "to_date": "",
                "description": "i Morgenposten",
                "authors": [
                    "Durbin, A."
                ],
                "comments": [],
                "archives": []
            },
            {
                "from_date": "1957",
                "order": "15",
                "reference": "s. 513–20 (ill.)",
                "to_date": "",
                "description": "Nye signaler i norsk skulptur, Ord och bild",
                "place": "Stockholm",
                "authors": [
                    "Scheldrup, A. G."
                ],
                "comments": [],
                "archives": []
            },
            {
                "from_date": "1947",
                "order": "46",
                "reference": "s. 27 (ill.)",
                "to_date": "",
                "description": "Bonytt",
                "authors": [],
                "comments": [],
                "archives": []
            },
            {
                "from_date": "1939-02-24",
                "order": "77",
                "to_date": "",
                "description": "Drammens Tidende",
                "authors": [],
                "comments": [],
                "archives": []
            },
            {
                "from_date": "1953-04-11",
                "order": "90",
                "reference": "(ill.)",
                "to_date": "",
                "description": "Verdens Gang",
                "authors": [],
                "comments": [],
                "archives": []
            },
            {
                "from_date": "1972",
                "order": "30",
                "reference": "bd. 18, s. 71, 74 (ill.)",
                "to_date": "",
                "description": "Aschehougs konversasjonsleksikon",
                "place": "Oslo",
                "authors": [],
                "comments": [],
                "archives": []
            },
            {
                "from_date": "1967",
                "order": "25",
                "reference": "register s. 323 (ill.)",
                "to_date": "",
                "description": "Norsk kunst i dag",
                "place": "Oslo",
                "authors": [
                    "Malmanger, M.",
                    "Parmann, Ø.",
                    "Matheson, F.",
                    "Askeland, J."
                ],
                "comments": [],
                "archives": []
            },
            {
                "from_date": "1971",
                "order": "63",
                "reference": "hefte 98 s. 47 (ill.)",
                "to_date": "",
                "description": "Kunsten idag",
                "authors": [],
                "comments": [],
                "archives": []
            },
            {
                "from_date": "1942",
                "order": "2",
                "reference": "s. 388–89 (ill.)",
                "to_date": "",
                "description": "Norges kunst",
                "place": "Oslo",
                "authors": [
                    "Østby, L.",
                    "Lexow, E."
                ],
                "comments": [
                    "i"
                ],
                "archives": []
            },
            {
                "from_date": "1972-05-12",
                "order": "113",
                "to_date": "",
                "description": "i Verdens Gang",
                "authors": [
                    "Michelet, J. F."
                ],
                "comments": [],
                "archives": []
            },
            {
                "from_date": "1945-12-10",
                "order": "83",
                "reference": "(ill.)",
                "to_date": "",
                "description": "Nationen",
                "authors": [],
                "comments": [],
                "archives": []
            },
            {
                "from_date": "1961-06-21",
                "order": "102",
                "to_date": "",
                "description": "i Verdens Gang",
                "authors": [
                    "Michelet, J. F."
                ],
                "comments": [],
                "archives": []
            },
            {
                "from_date": "1975",
                "order": "70",
                "reference": "s. 63, 110",
                "to_date": "",
                "description": "Kunst og Kultur",
                "authors": [],
                "comments": [],
                "archives": []
            },
            {
                "from_date": "1941-02-11",
                "order": "78",
                "to_date": "",
                "description": "i Morgenbladet",
                "authors": [
                    "Durbin, A. Hansen"
                ],
                "comments": [],
                "archives": []
            },
            {
                "from_date": "1956",
                "order": "12",
                "reference": "s. 254 (ill.)",
                "to_date": "",
                "description": "Illustrert Norsk Kunstnerleksikon",
                "place": "Oslo",
                "authors": [],
                "comments": [],
                "archives": []
            },
            {
                "from_date": "1964",
                "order": "50",
                "reference": "s. 284",
                "to_date": "",
                "description": "Bonytt",
                "authors": [],
                "comments": [],
                "archives": []
            },
            {
                "from_date": "1960-10-18",
                "order": "97",
                "to_date": "",
                "description": "i Aftenposten",
                "authors": [
                    "Revold, R."
                ],
                "comments": [],
                "archives": []
            },
            {
                "from_date": "1946",
                "order": "45",
                "reference": "s. 9–10, 194–95 (ill.)",
                "to_date": "",
                "description": "Bonytt",
                "authors": [],
                "comments": [],
                "archives": []
            },
            {
                "from_date": "1977-10-22",
                "order": "123",
                "to_date": "",
                "description": "i Dagbladet",
                "authors": [
                    "Flor, H."
                ],
                "comments": [],
                "archives": []
            },
            {
                "from_date": "1949-04-09",
                "order": "89",
                "reference": "(ill.)",
                "to_date": "",
                "description": "Nationen",
                "authors": [],
                "comments": [],
                "archives": []
            },
            {
                "from_date": "1941",
                "order": "43",
                "reference": "nr. 4 s. 4",
                "to_date": "",
                "description": "Tidsskrifter:Bonytt",
                "authors": [],
                "comments": [],
                "archives": []
            },
            {
                "from_date": "1967",
                "order": "24",
                "reference": "s. 122, 162, 172",
                "to_date": "",
                "description": "Telemark i norsk billedhuggerkunst",
                "place": "(Skien",
                "authors": [
                    "Østvedt, E."
                ],
                "comments": [],
                "archives": []
            },
            {
                "from_date": "1970",
                "order": "29",
                "reference": "nr. 1, s. 16–17 (ill.)",
                "to_date": "",
                "description": "Per Palle Storm, Kunst og Kunstnere",
                "place": "Oslo",
                "authors": [
                    "Døhlen, A."
                ],
                "comments": [],
                "archives": []
            },
            {
                "from_date": "1973",
                "order": "64",
                "reference": "hefte 104 s. 6 (ill.)",
                "to_date": "",
                "description": "Kunsten idag",
                "authors": [],
                "comments": [],
                "archives": []
            },
            {
                "from_date": "1983",
                "order": "38",
                "reference": "bd. 7, s. 294–98 (ill.)",
                "to_date": "",
                "description": "i Norges kunsthistorie",
                "place": "Oslo",
                "authors": [
                    "Flor, H."
                ],
                "comments": [],
                "archives": []
            },
            {
                "from_date": "1942",
                "order": "1",
                "reference": "s. 2, 106–07, 118 (ill.)",
                "to_date": "",
                "description": "Norsk skulptur gjennom hundre år",
                "place": "Oslo",
                "authors": [
                    "Durbin, A."
                ],
                "comments": [],
                "archives": []
            },
            {
                "from_date": "1972-05-09",
                "order": "112",
                "to_date": "",
                "description": "i Morgenbladet",
                "authors": [
                    "Egeland, E."
                ],
                "comments": [],
                "archives": []
            },
            {
                "from_date": "1947-02-04",
                "order": "84",
                "to_date": "",
                "description": "Dagbladet",
                "authors": [],
                "comments": [],
                "archives": []
            },
            {
                "from_date": "1965",
                "order": "58",
                "reference": "hefte 71 s. 43-44",
                "to_date": "",
                "description": "Kunsten idag",
                "authors": [],
                "comments": [],
                "archives": []
            },
            {
                "from_date": "1966-09-09",
                "order": "103",
                "reference": "(ill.)",
                "to_date": "",
                "description": "i Berlingske Tidende",
                "place": "København",
                "authors": [
                    "Zibrandtsen, J."
                ],
                "comments": [],
                "archives": []
            },
            {
                "from_date": "1972",
                "order": "69",
                "reference": "s. 115, 182, 260",
                "to_date": "",
                "description": "Kunst og Kultur",
                "authors": [],
                "comments": [],
                "archives": []
            },
            {
                "from_date": "1959",
                "order": "49",
                "reference": "s. 230–31 (ill.)",
                "to_date": "",
                "description": "Bonytt",
                "authors": [],
                "comments": [],
                "archives": []
            },
            {
                "from_date": "1956",
                "order": "13",
                "reference": "s. 62 (ill.)",
                "to_date": "",
                "description": "Monumenter og prydskulptur i Oslo",
                "place": "Oslo",
                "authors": [],
                "comments": [
                    "katalog Oslo kommunes kunstsamlinger, nr. 12"
                ],
                "archives": []
            },
            {
                "from_date": "1944",
                "order": "44",
                "reference": "s. 34",
                "to_date": "",
                "description": "Bonytt",
                "authors": [],
                "comments": [],
                "archives": []
            },
            {
                "from_date": "1977-10-21",
                "order": "122",
                "reference": "(ill.)",
                "to_date": "",
                "description": "i Morgenbladet",
                "authors": [
                    "Hopstock, K."
                ],
                "comments": [],
                "archives": []
            },
            {
                "from_date": "1960-10-18",
                "order": "98",
                "reference": "(ill.)",
                "to_date": "",
                "description": "i Dagbladet",
                "authors": [
                    "Mæhle, O."
                ],
                "comments": [],
                "archives": []
            },
            {
                "from_date": "1958",
                "order": "61",
                "reference": "hefte 83 s. 6-8",
                "to_date": "",
                "description": "Kunsten idag",
                "authors": [],
                "comments": [],
                "archives": []
            },
            {
                "from_date": "1941",
                "order": "0",
                "reference": "s. 82, 105",
                "to_date": "",
                "description": "Norsk grafikk i det tyvende århundre",
                "place": "Oslo",
                "authors": [
                    "Sinding-Larsen, S."
                ],
                "comments": [],
                "archives": []
            },
            {
                "from_date": "1953-04-22",
                "order": "92",
                "to_date": "",
                "description": "i Aftenposten",
                "authors": [
                    "Stenstadvold, H."
                ],
                "comments": [],
                "archives": []
            },
            {
                "from_date": "1977",
                "order": "33",
                "to_date": "",
                "description": "Agder Bygd og by i Norge",
                "place": "Oslo",
                "authors": [],
                "comments": [
                    "register"
                ],
                "archives": []
            },
            {
                "from_date": "1953",
                "order": "9",
                "reference": "bd. 2, s. 428–30 (ill.)",
                "to_date": "",
                "description": "Norges billedkunst",
                "place": "Oslo",
                "authors": [
                    "Revold, R."
                ],
                "comments": [],
                "archives": []
            },
            {
                "from_date": "1967",
                "order": "23",
                "reference": "s. 85 (ill.)",
                "to_date": "",
                "description": "Vandring i Nationaltheatret",
                "place": "Oslo",
                "authors": [
                    "Røine, E."
                ],
                "comments": [],
                "archives": []
            },
            {
                "from_date": "1972-05-16",
                "order": "115",
                "to_date": "",
                "description": "i Arbeiderbladet",
                "authors": [
                    "Dæhlin, E. O."
                ],
                "comments": [],
                "archives": []
            },
            {
                "from_date": "1960-12-02",
                "order": "100",
                "to_date": "",
                "description": "i Morgenbladet",
                "authors": [
                    "Parmann, Ø."
                ],
                "comments": [],
                "archives": []
            },
            {
                "from_date": "1941-11-24",
                "order": "82",
                "reference": "(ill.)",
                "to_date": "",
                "description": "i Dagbladet",
                "authors": [
                    "Nielsen, F."
                ],
                "comments": [],
                "archives": []
            },
            {
                "from_date": "1976",
                "order": "71",
                "reference": "s. 50, 179",
                "to_date": "",
                "description": "Kunst og Kultur",
                "authors": [],
                "comments": [],
                "archives": []
            },
            {
                "from_date": "1977-10-17",
                "order": "121",
                "reference": "(ill.)",
                "to_date": "",
                "description": "i Verdens Gang",
                "authors": [
                    "Michelet, J. F."
                ],
                "comments": [],
                "archives": []
            },
            {
                "from_date": "1947",
                "order": "52",
                "reference": "hefte 4 s. 54 (ill.)",
                "to_date": "",
                "description": "Kunsten idag",
                "authors": [],
                "comments": [],
                "archives": []
            },
            {
                "from_date": "1968-06-22",
                "order": "108",
                "reference": "(ill.)",
                "to_date": "",
                "description": "Harstad Tidende",
                "authors": [],
                "comments": [],
                "archives": []
            },
            {
                "from_date": "1970",
                "order": "28",
                "reference": "(upag.) (ill.)",
                "to_date": "",
                "description": "Skulptur i Moss",
                "place": "Oslo",
                "authors": [
                    "Viskum, O. Hagen"
                ],
                "comments": [],
                "archives": []
            },
            {
                "from_date": "1963",
                "order": "18",
                "reference": "s. 32, 112–13, 129 (ill.)",
                "to_date": "",
                "description": "Norsk tegnekunst i Nasjonalgalleriet",
                "place": "Oslo",
                "authors": [
                    "Østby, L."
                ],
                "comments": [],
                "archives": []
            },
            {
                "from_date": "1977",
                "order": "32",
                "reference": "register (ill.)",
                "to_date": "",
                "description": "Norges kunsthistorie",
                "place": "Oslo",
                "authors": [
                    "Østby, L."
                ],
                "comments": [],
                "archives": []
            },
            {
                "from_date": "1952",
                "order": "8",
                "reference": "s. 155 (ill.)",
                "to_date": "",
                "description": "Norsk illustrasjonskunst 1850–1950",
                "place": "Oslo",
                "authors": [
                    "Sundseth, A. B.",
                    "Melhus, A. C."
                ],
                "comments": [],
                "archives": []
            },
            {
                "from_date": "1948",
                "order": "42",
                "to_date": "1984",
                "description": "Hvem er hvem?",
                "place": "Oslo",
                "authors": [],
                "comments": [
                    "Tidsskrifter"
                ],
                "archives": []
            },
            {
                "from_date": "1953-04-17",
                "order": "91",
                "to_date": "",
                "description": "i Dagbladet",
                "authors": [
                    "Steen-Johnsen, S."
                ],
                "comments": [],
                "archives": []
            },
            {
                "from_date": "1970",
                "order": "62",
                "reference": "hefte 92 s. 27",
                "to_date": "",
                "description": "Kunsten idag",
                "authors": [],
                "comments": [],
                "archives": []
            },
            {
                "from_date": "1980-04-25",
                "order": "128",
                "reference": "(ill.)",
                "to_date": "",
                "description": "Aftenposten",
                "authors": [],
                "comments": [],
                "archives": []
            },
            {
                "from_date": "1972-05-13",
                "order": "114",
                "reference": "(ill.)",
                "to_date": "",
                "description": "i Aftenposten",
                "authors": [
                    "Johnsrud, E. H."
                ],
                "comments": [],
                "archives": []
            },
            {
                "from_date": "1966",
                "order": "22",
                "reference": "s. 88–89",
                "to_date": "",
                "description": "Norsk Biografisk Leksikon",
                "place": "Oslo",
                "authors": [],
                "comments": [],
                "archives": []
            },
            {
                "from_date": "1961-06-19",
                "order": "101",
                "to_date": "",
                "description": "Morgenbladet",
                "authors": [],
                "comments": [],
                "archives": []
            },
            {
                "from_date": "1955",
                "order": "10",
                "reference": "s. 271",
                "to_date": "",
                "description": "Trondhjems Kunstforening 1845–1945",
                "place": "Trondheim",
                "authors": [
                    "Grimelund, J. J.",
                    "Flønes, O."
                ],
                "comments": [],
                "archives": []
            },
            {
                "from_date": "1976-02-02",
                "order": "120",
                "reference": "(ill.)",
                "to_date": "",
                "description": "i Morgenbladet",
                "authors": [
                    "Grøtvedt, P."
                ],
                "comments": [],
                "archives": []
            },
            {
                "from_date": "1941-11-22",
                "order": "81",
                "reference": "(ill.)",
                "to_date": "",
                "description": "i Aftenposten",
                "authors": [
                    "Willoch, S."
                ],
                "comments": [],
                "archives": []
            },
            {
                "from_date": "1977",
                "order": "72",
                "reference": "s. 51",
                "to_date": "",
                "description": "Kunst og Kultur",
                "authors": [],
                "comments": [],
                "archives": []
            },
            {
                "from_date": "1946",
                "order": "51",
                "reference": "s. 17 (ill.)",
                "to_date": "",
                "description": "Julehelg",
                "place": "Oslo",
                "authors": [],
                "comments": [],
                "archives": []
            },
            {
                "from_date": "1956",
                "order": "11",
                "reference": "s. 75 (ill.)",
                "to_date": "",
                "description": "Norske grafikere",
                "place": "Olso",
                "authors": [],
                "comments": [],
                "archives": []
            },
            {
                "from_date": "1952",
                "order": "7",
                "reference": "bd. 2 s. 35, 201–04 (ill.)",
                "to_date": "",
                "description": "Rådhuset i Oslo",
                "place": "Oslo",
                "authors": [
                    "Just, C."
                ],
                "comments": [],
                "archives": []
            },
            {
                "from_date": "1965",
                "order": "21",
                "reference": "s. 100",
                "to_date": "",
                "description": "106 norske grafikere",
                "place": "Oslo",
                "authors": [],
                "comments": [],
                "archives": []
            },
            {
                "from_date": "1975",
                "order": "31",
                "reference": "s. 225",
                "to_date": "",
                "description": "Telemark. Bygd og by i Norge",
                "place": "Oslo",
                "authors": [],
                "comments": [],
                "archives": []
            },
            {
                "from_date": "1984",
                "order": "41",
                "reference": "s. 17–18",
                "to_date": "",
                "description": "Kunstakademiets professorer gjennom 75 år",
                "place": "Oslo",
                "authors": [
                    "Thue, O."
                ],
                "comments": [
                    "katalog Nasjonalgalleriet"
                ],
                "archives": []
            },
            {
                "from_date": "1980-04-23",
                "order": "127",
                "to_date": "",
                "description": "Verdens Gang",
                "authors": [],
                "comments": [],
                "archives": []
            },
            {
                "from_date": "",
                "order": "35",
                "reference": "s. 92–93",
                "to_date": "",
                "description": "Kunstnernes Hus 1930–1980",
                "authors": [
                    "Gjessing, S. (red.)"
                ],
                "comments": [],
                "archives": []
            },
            {
                "from_date": "1958-05-30",
                "order": "94",
                "to_date": "",
                "description": "i Dagbladet",
                "authors": [
                    "Steen, K."
                ],
                "comments": [],
                "archives": []
            },
            {
                "from_date": "1966",
                "order": "59",
                "reference": "hefte 77 s. 27, 41",
                "to_date": "",
                "description": "Kunsten idag",
                "authors": [],
                "comments": [],
                "archives": []
            },
            {
                "from_date": "1970-12-01",
                "order": "109",
                "to_date": "",
                "description": "Dagbladet",
                "authors": [],
                "comments": [],
                "archives": []
            },
            {
                "from_date": "1947-03-08",
                "order": "88",
                "reference": "(ill.)",
                "to_date": "",
                "description": "i Aftenposten",
                "authors": [
                    "Gran, H."
                ],
                "comments": [],
                "archives": []
            },
            {
                "from_date": "1954",
                "order": "55",
                "reference": "hefte 19–30 s. 12",
                "to_date": "",
                "description": "Kunsten idag",
                "authors": [],
                "comments": [],
                "archives": []
            },
            {
                "from_date": "1941-02-19",
                "order": "80",
                "to_date": "",
                "description": "i Aftenposten",
                "authors": [
                    "Willoch, S."
                ],
                "comments": [],
                "archives": []
            },
            {
                "from_date": "1976-01-28",
                "order": "119",
                "reference": "(ill.)",
                "to_date": "",
                "description": "i Arbeiderbladet",
                "authors": [
                    "Storsletten, O."
                ],
                "comments": [],
                "archives": []
            },
            {
                "from_date": "1976-01-24",
                "order": "117",
                "reference": "(ill.)",
                "to_date": "",
                "description": "i Aftenposten",
                "authors": [
                    "Egeland, E."
                ],
                "comments": [],
                "archives": []
            },
            {
                "from_date": "1971",
                "order": "68",
                "reference": "s. 16",
                "to_date": "",
                "description": "Kunst og Kultur",
                "authors": [],
                "comments": [],
                "archives": []
            },
            {
                "from_date": "1978",
                "order": "73",
                "reference": "s. 51",
                "to_date": "",
                "description": "Kunst og Kultur",
                "authors": [],
                "comments": [],
                "archives": []
            },
            {
                "from_date": "1950",
                "order": "6",
                "reference": "bd. 1, s. 230",
                "to_date": "",
                "description": "Rådhuset i Oslo",
                "place": "Oslo",
                "authors": [
                    "Just, C."
                ],
                "comments": [],
                "archives": []
            },
            {
                "from_date": "1965",
                "order": "20",
                "reference": "register, s. 397",
                "to_date": "",
                "description": "Norske Portretter. Videnskapsmenn",
                "place": "Oslo",
                "authors": [],
                "comments": [],
                "archives": []
            },
            {
                "from_date": "1950",
                "order": "54",
                "reference": "hefte 13–14 s. 16",
                "to_date": "",
                "description": "Kunsten idag",
                "authors": [],
                "comments": [],
                "archives": []
            },
            {
                "from_date": "1983",
                "order": "40",
                "reference": "s. 6, 11, 15, 18–19, 26, 150",
                "to_date": "",
                "description": "i Norske billedhoggere i dag",
                "place": "Oslo",
                "authors": [
                    "Brun, H.-J."
                ],
                "comments": [],
                "archives": []
            },
            {
                "from_date": "1947-03-20",
                "order": "87",
                "to_date": "",
                "description": "Morgenbladet",
                "authors": [],
                "comments": [],
                "archives": []
            },
            {
                "from_date": "1967-01-23",
                "order": "106",
                "reference": "(ill.)",
                "to_date": "",
                "description": "Aftenposten",
                "authors": [],
                "comments": [],
                "archives": []
            },
            {
                "from_date": "1960",
                "order": "16",
                "reference": "s. 116, 141, 147, 160 (ill.)",
                "to_date": "",
                "description": "Streiftog og glimt",
                "place": "Oslo",
                "authors": [
                    "Mæhle, O."
                ],
                "comments": [],
                "archives": []
            },
            {
                "from_date": "1978",
                "order": "34",
                "reference": "bd. 2, s. 66, 68–69, 77 (ill.)",
                "to_date": "",
                "description": "Østfold. Bygd og by i Norge",
                "place": "Oslo",
                "authors": [],
                "comments": [],
                "archives": []
            },
            {
                "from_date": "1980-04-19",
                "order": "126",
                "to_date": "",
                "description": "i Aftenposten",
                "authors": [
                    "Bugge, E. Moestue"
                ],
                "comments": [],
                "archives": []
            },
            {
                "from_date": "1957-03-09",
                "order": "93",
                "reference": "(ill.)",
                "to_date": "",
                "description": "Verdens Gang",
                "authors": [],
                "comments": [],
                "archives": []
            },
            {
                "from_date": "1941-11-19",
                "order": "79",
                "to_date": "",
                "description": "i Morgenbladet",
                "authors": [
                    "Durbin, A. Hansen"
                ],
                "comments": [],
                "archives": []
            },
            {
                "from_date": "1967",
                "order": "60",
                "reference": "hefte 79 s. 5",
                "to_date": "",
                "description": "Kunsten idag",
                "authors": [],
                "comments": [],
                "archives": []
            },
            {
                "from_date": "1980-06-03",
                "order": "129",
                "to_date": "",
                "description": "Dagbladet",
                "authors": [],
                "comments": [],
                "archives": []
            },
            {
                "from_date": "1979",
                "order": "74",
                "reference": "s. 108",
                "to_date": "",
                "description": "Kunst og Kultur",
                "authors": [],
                "comments": [],
                "archives": []
            },
            {
                "from_date": "1960-10-20",
                "order": "99",
                "reference": "(ill.)",
                "to_date": "",
                "description": "i Morgenbladet",
                "authors": [
                    "Parmann, Ø."
                ],
                "comments": [],
                "archives": []
            },
            {
                "from_date": "1975-05-22",
                "order": "116",
                "reference": "(ill.)",
                "to_date": "",
                "description": "Varden",
                "authors": [],
                "comments": [],
                "archives": []
            },
            {
                "from_date": "1951",
                "order": "48",
                "reference": "s. 5",
                "to_date": "",
                "description": "Bonytt",
                "authors": [],
                "comments": [],
                "archives": []
            },
            {
                "from_date": "1948",
                "order": "5",
                "reference": "hefte 5, s. 17–33",
                "to_date": "",
                "description": "Per Palle Storm, Kunsten idag",
                "authors": [
                    "Durbin, A."
                ],
                "comments": [],
                "archives": []
            },
            {
                "from_date": "1964",
                "order": "19",
                "reference": "s. 58",
                "to_date": "",
                "description": "Nordisk skulptur",
                "place": "København",
                "authors": [
                    "Bøyesen, L. Rostrup (red.)"
                ],
                "comments": [],
                "archives": []
            },
            {
                "from_date": "1948",
                "order": "53",
                "reference": "hefte 5 s. 16–33 (ill.)",
                "to_date": "",
                "description": "Kunsten idag",
                "authors": [],
                "comments": [],
                "archives": []
            },
            {
                "from_date": "1967-01-26",
                "order": "107",
                "to_date": "",
                "description": "i Morgenbladet",
                "authors": [
                    "Parmann, Ø."
                ],
                "comments": [],
                "archives": []
            },
            {
                "from_date": "1983",
                "order": "39",
                "reference": "s. 5, 110 (ill.)",
                "to_date": "",
                "description": "Kongens slott",
                "place": "Oslo",
                "authors": [
                    "Hjelde, G.",
                    "Kavli, G."
                ],
                "comments": [],
                "archives": []
            },
            {
                "from_date": "1960",
                "order": "17",
                "reference": "s. 616, 663 (ill.)",
                "to_date": "",
                "description": "Norsk kunstnerliv",
                "place": "Oslo",
                "authors": [
                    "Schulerud, M."
                ],
                "comments": [],
                "archives": []
            }
        ],
        "archives": [],
        "radio_and_tv_programs": []
    },
    "title": "Per Palle Storm",
    "url": "https://nkl.snl.no/Per_Palle_Storm",
    "subject_url": "http://snl.no/.taxonomy/3405",
    "subject_title": "Norsk kunstnerleksikon",
    "xhtml_body": "<div>\r\n<p>S. vokste opp i Buenos Aires. Sin første skulpturundervisning fikk han hos spanjolene Bartholomé Tasso og Urbici Solér i 1927–29. Den siste var en streng lærer som nådeløst rev ned det han ikke anså som god skulptur. I 1930 reiste S. til Europa og besøkte Italia og Berlin før han kom til Oslo og begynte på Kunstakademiet under Wilhelm Rasmussen. Med sin kosmopolitiske bakgrunn og sterke personlighet markerte S. seg tidlig blant sine medelever. I 1933 leide S. atelier i Paris. Her studerte han klassisk skulptur og var særlig opptatt av Rodin. Samme år debuterte han på Høstutstillingen og vant 3. premie i konkurransen om Ankerbroens utsmykking. Han fikk flere gode plasseringer i skulpturkonkurranser, bl.a. to premierte utkast i Landsorganisasjonens konkurranse i 1937 om Arbeiderbevegelsens monument på Youngstorget, Oslo. To år senere fikk han et endelig utkast godkjent, men skulpturen ble ikke utført. Først flere år etter krigen ble denne ideen igjen tatt opp, og da i en helt annen form. I 1939 vant S. konkurransen om <em>Thorleif Haug-monumentet</em>, Drammen (bronse 1941/42, avduket 1946), landets første monument over en idrettsutøver. Figuren er fremstilt stående, iført omfangsrike sportsklær med ski og staver i hendene, klar til fysisk utfoldelse.</p>\r\n<p>S. evne til god personkarakteristikk kommer klart til syne i hans portretter. <em>Pike fra Risør</em> (bronse 1938, Nasjonalgalleriet, Oslo) er et sjarmerende arbeid med spontant preg, mens portrettet av <em>Alfred Seland</em> (bronse 1938, Haugesund Billedgalleri) har en forenklet uttrykksform med faste trekk av nesten ornamental karakter. Bysten av <em>Rolf Stenersen</em> (bronse 1941, privat eie) er avslørende realistisk, uten skjønnhet, men med kraft og styrke bak de oppsvulmede trekkene. I 1941 karakteriserte S. seg som \"naturalist – innbitt og forbanna naturalist\", en programerklæring han har holdt fast ved gjennom hele sitt kunstnerlige virke. For S. gir naturen i sin foranderlighet stadig nye utfordringer. Han ser mennesket som et objekt med endeløse variasjonsmuligheter der formen er gitt av spillet mellom muskler og skjelett. Hans naturalisme kan grense til det fanatiske, men er gjennomført med konsekvens. <em>Sittende atlet</em> (bronse 1941, Nasjonalgalleriet) viser med hvilken overlegen dyktighet S. fremstiller menneskekroppen. Figuren sitter avslappet fremoverbøyd med hodet støttet mot den ene hånden. Kroppen er i ro, men likevel spiller musklene under huden og gir skulpturen potensiell energi. I <em>Sammenkrøket kvinne</em> (bronse 1945, Kristiansand) er leggmusklene presset flate mot lårene mens tærne krøker seg rundt plinten og ryggen blir strukket lang i det hun slår armene rundt bena. Skulpturen er ikke bærer av et emosjonelt innhold, men en inntrengende studie i den menneskelige anatomi. Til denne gruppe arbeider hører også <em>Mann som drikker</em> (bronse 1960, Kronprinsesse Märthas plass); igjen en naken, sammenhuket, fremoverbøyd skikkelse sitrende av konsentrert energi i det munnen møter kanten av skålen. Denne sluttede form eksponerer samtidig kroppens konstruksjon og musklene under hudens stramme skinn. S.'større arbeider er hovedsakelig i bronse, men han har også utført arbeider i granitt som <em>Familien</em> (1943/44) i Halden, en mer stilisert gruppe der blokkvirkningen kommer godt fram. Etter 1945 utførte S. flere krigsmonumenter, bl.a. <em>Monument over de falne</em> (bronse 1948) i Sarpsborg, der en naken mannsfigur hviler på lit de parade, og <em>Krigsmonument</em> (bronse ca. 1952) ved Ris kirke, Oslo. Monumentet over <em>Kong Haakon</em> (bronse 1950) i Kristiansand, har en sterk symbolverdi gitt av selve formen. Kongens lange skikkelse er gjort enda lenger, han står rank mot vinden med det ene ben skutt fram. Arbeidet har monumentalitet og er samtidig et treffende portrett. S. bygde videre på samme idé i sitt konkurranseutkast til kongemonument i Oslo kalt \"Pilar\" (1967), der kongen står verdig med hendene samlet i rolig andektighet. Utkastet fikk tredjepremie, men ble innkjøpt av Tromsø kommune og oppført i Rådhusparken (bronse 1969) . S. fungerte som lærer ved Det illegale akademi under 2. verdenskrig, og da professoratet i skulptur ved Kunstakademiet ble utlyst i 1946, var han en av tre søkere. Grunnet konflikt mellom Bildende Kunstneres Styre og Norsk Billedhuggerforening ble det avholdt en konkurranseutstilling i Kunstnernes Hus. Resultatet var at S. i 1947 ble utnevnt til professor.</p>\r\n<p>S.' arbeidsskulpturer foran Oslo rådhus (bronse 1951–60) er i sin sosialrealistiske form en videreføring av Charles Meuniers og Jules Dalous arbeiderskildringer. De seks figurene er detaljert gjennomarbeidet og representerer forskjellige yrkesgrupper. <em>Steinbryteren</em> (1960) har størst individualitet. Den voluminøse, nesten grotesk realistiske skikkelsen støtter spettet mot bakken og hviler den andre hånden mot hoften i et nesten utfordrende uttrykk. Skulpturene var planlagt for Rådhushallen, og den nåværende plassering på Rådhustrappen fungerer dårlig sammen med arkitekturen. I samme gruppe av heroiserende skulptur hører monumentet over <em>Arbeiderbevegelsens pionerer</em> (bronse 1955, avduket 1958) foran Folkets Hus, Oslo. Den monumentale skulpturen fremstiller en sleggebærer og er en videreføring av ideen fra før krigen om et Arbeiderbevegelsens monument. S. omarbeidet totalt sine opprinnelige utkast og i sin nye form er monumentet blitt et idealisert bilde av arbeideren på marsj fremover. Plasseringen i ytterkanten av Youngstorget gjør at monumentet virker mindre dominerende, til tross for dimensjonene (nesten 6 meter). Med sin interesse for det individuelle lykkes S. ikke alltid i sine arbeiderfremstillinger. Den store produksjonen av portrettbyster viser S.' evne til fordypning i modellens fysiognomi og å la objektets karakter bestemme stilbilde og overflatebehandling. Bysten av <em>Ingeborg Storm</em>, kunstnerens hustru (bronse 1955, Nasjonalgalleriet) er et renessanseinspirert arbeid, stramt formet og inntrengende i karakteristikken. Hodet av <em>professor H.P. L'Orange</em> (bronse 1960, Det Norske institutt i Roma), minner i sitt uttrykk om et romersk keiserportrett. Flere av S.' arbeider er av mer impresjonistisk karakter, som bysten av <em>Claes Gill</em> (bronse 1973, Nasjonalgalleriet), der ansiktet får liv gjennom lys og skyggevirkninger. S. har gjennomført en rekke gode arbeider i mindre format. <em>Ridende jockey</em> (bronse 1958, Norges idrettshøgskole) fanger selve bevegelsen og <em>Ung pike</em> (bronse 1974, Nasjonalgalleriet) er en av mange studier av den kvinnelige anatomi. <em>Liggende løvinne</em> (bronse 1970, Nasjonalgalleriet) fremstiller kattedyret som en genial konstruksjon av skjelett og muskler i doven bevegelse.</p>\r\n<p>S. har også markert seg som tegner og grafiker med stor variasjon i motiv og teknikk. Han har utstilt minutiøse strektegninger av flaggermus og fuglevinger, raske skisser og rødkrittegninger av eksotiske dyr fra Europas dyreparker og romantiske naturstudier i penn og lavering. Begeistringen for de gamle mestere slår ofte igjennom, som i illustrasjonene til Benvenuto Cellinis selvbiografi (1946), der renessansepreget faller heldig sammen med bokens emne. S. har utført Norges myntserie fra 1958 og en rekke medaljer av fremragende kvalitet, bl.a. de av <em> Direktør Anders Sandvig</em> (1942) og <em>Direktør Jens Thiis</em> (1951) i Museumsforbundets serie. S. var professor ved Kunstakademiet fra 1947 til -80, lenger enn noen annen og med ansvaret for den høyere skulpturutdannelse i landet. Han var en nesten fanatisk forkjemper for et naturalistisk program og fastholdt for elevene et anatomisk inntrengende akt- og portrettstudium. Hans omfattende anatomiske kunnskaper og samhørighet med fortidens mestere ble entusiastisk formidlet og gav hans elever et solid naturalistisk fundament. Etter hvert medførte imidlertid hans steilt naturalistiske kunstsyn og fornektelse av modernismens ytringer konflikter med mange elever. Under nyrealismen fikk S.' pedagogiske prinsipper ny aktualitet.</p>\r\n\r\n</div>",
    "created_at": "2014-12-21T14:55:19.146+01:00",
    "changed_at": "2024-06-18T23:28:18.561+02:00",
    "license_name": "begrenset",
    "metadata_license_name": "fri",
    "metadata": {
        "gender": "m",
        "same_as": "[\"http://data.nasjonalmuseet.no/resource/person_8736ab3575\",\"https://digitaltmuseum.no/d08a2d07-fbd2-4350-b72f-62e17cd1406e\",\"http://kulturnav.org/d08a2d07-fbd2-4350-b72f-62e17cd1406e\"]",
        "lastname": "Storm",
        "firstname": "Per Palle",
        "birth_date": "1.12.1910",
        "birthplace": "København",
        "death_date": "6.1.1994",
        "external_id": "person_8736ab3575",
        "kulturnav_id": "d08a2d07-fbd2-4350-b72f-62e17cd1406e"
    },
    "authors": [
        {
            "full_name": "Elsebet Kjerschow"
        }
    ],
    "images": [
        {
            "copyright": null,
            "license": "Gjengitt med tillatelse",
            "standard_size_url": "https://media.snl.no/media/20604/standard_NMK-B_NG.K_26H.B.0755020151204-26003-srsd6b.jpg",
            "full_size_url": "https://media.snl.no/media/20604/NMK-B_NG.K_26H.B.0755020151204-26003-srsd6b.jpg",
            "xhtml": "<div><p><i>Liggende løve</i>. 1938. <a href=\"http://digitaltmuseum.no/011042462525\">Digitalt Museum</a></p></div>",
            "type": "image",
            "heading": "Per Palle Storm",
            "paragraph_index": 0
        },
        {
            "copyright": null,
            "license": "Gjengitt med tillatelse",
            "standard_size_url": "https://media.snl.no/media/20605/standard_NMK-B_NG.K_26H.B.0840520151204-26003-1s7ndcx.jpg",
            "full_size_url": "https://media.snl.no/media/20605/NMK-B_NG.K_26H.B.0840520151204-26003-1s7ndcx.jpg",
            "xhtml": "<div><p><i>Sammenkrøket akt</i>. <a href=\"http://digitaltmuseum.no/011042465242\">Digitalt Museum</a></p></div>",
            "type": "image",
            "heading": "Per Palle Storm",
            "paragraph_index": 0
        },
        {
            "copyright": null,
            "license": "Gjengitt med tillatelse",
            "standard_size_url": "https://media.snl.no/media/20606/standard_NMK-B_NG.S.0125520151204-26003-176twb1.jpg",
            "full_size_url": "https://media.snl.no/media/20606/NMK-B_NG.S.0125520151204-26003-176twb1.jpg",
            "xhtml": "<div><p><i>Pike fra Risør</i>. <a href=\"http://digitaltmuseum.no/021045728747\">Digitalt Museum</a></p></div>",
            "type": "image",
            "heading": "Per Palle Storm",
            "paragraph_index": 0
        },
        {
            "copyright": null,
            "license": "Gjengitt med tillatelse",
            "standard_size_url": "https://media.snl.no/media/20607/standard_NMK-B_NG.S.0130620151204-26003-cixd99.jpg",
            "full_size_url": "https://media.snl.no/media/20607/NMK-B_NG.S.0130620151204-26003-cixd99.jpg",
            "xhtml": "<div><p><i>Sittende atlet</i>. 1942. <a href=\"http://digitaltmuseum.no/011041109345\">Digitalt Museum</a></p></div>",
            "type": "image",
            "heading": "Per Palle Storm",
            "paragraph_index": 0
        },
        {
            "copyright": null,
            "license": "Gjengitt med tillatelse",
            "standard_size_url": "https://media.snl.no/media/20608/standard_NMK-B_NG.S.0173720151204-26003-1v5tqu6.jpg",
            "full_size_url": "https://media.snl.no/media/20608/NMK-B_NG.S.0173720151204-26003-1v5tqu6.jpg",
            "xhtml": "<div><p><i>Elefant</i>. <a href=\"http://digitaltmuseum.no/011041109347\">Digitalt Museum</a></p></div>",
            "type": "image",
            "heading": "Per Palle Storm",
            "paragraph_index": 0
        }
    ],
    "professions": [
        {
            "description": "tegner"
        },
        {
            "description": "billedhugger"
        },
        {
            "description": "grafiker"
        }
    ]
}