{
    "id": 418028,
    "headword": "Peter Anderssønn Lillie",
    "custom_metadata_json": {
        "professions": [
            {
                "description": "kontrafeier"
            }
        ],
        "others": [],
        "relations": [],
        "residences": [],
        "educations": [
            {
                "comment": "Trolig utdannelse i Sverige, muligens Hälsingland før 1671",
                "order": "0"
            }
        ],
        "travels": [],
        "memberships": [],
        "awards": [],
        "public_productions": [
            {
                "from_date": "",
                "order": "28",
                "to_date": "",
                "description": "altertavle, prekestol og galleribrystning Vuku kirke (1699)"
            },
            {
                "from_date": "",
                "order": "22",
                "to_date": "",
                "description": "bilde i Støren kirke"
            },
            {
                "from_date": "",
                "order": "61",
                "to_date": "",
                "description": "Nordenfjeldske Kunstindustrimuseum, Trondheim"
            },
            {
                "from_date": "",
                "order": "32",
                "to_date": "",
                "description": "altertavle Singsås kirke (1699, Glomdalsmuseet)"
            },
            {
                "from_date": "",
                "order": "57",
                "to_date": "",
                "description": "sogneprest Hans Holtermann som barn (Nordenfjeldske Kunstindustrimuseum, Trondheim)"
            },
            {
                "from_date": "",
                "order": "42",
                "to_date": "",
                "description": "prestepar Norddal kirke (1673)"
            },
            {
                "from_date": "",
                "order": "51",
                "to_date": "",
                "description": "sogneprest P. Mentzen Darre d.y., Melhus kirke (1709)"
            },
            {
                "from_date": "",
                "order": "52",
                "to_date": "",
                "description": "sogneprest Iver Paalsen (1710, Historisk Museum Bergen)"
            },
            {
                "from_date": "",
                "order": "33",
                "to_date": "",
                "description": "altertavle, døpefont og prekestol Haltdalen kirke (1702, Det Kongelige Norske Videnskabers Selskab, Trondheim)"
            },
            {
                "from_date": "",
                "order": "21",
                "to_date": "",
                "description": "angivelig i Horg og Leinstrand kirker (slutten av 1670-årene, begynnelsen av 1680-årene)"
            },
            {
                "from_date": "",
                "order": "26",
                "to_date": "",
                "description": "altertavle Rein kirke (1692)"
            },
            {
                "from_date": "",
                "order": "37",
                "to_date": "",
                "description": "del av altertavle, fyllinger fra prekestol og døpefont (1705, senere overmalt) Tolga kirke"
            },
            {
                "from_date": "",
                "order": "47",
                "to_date": "",
                "description": "sogneprest Jens Bloch og hustru, sogneprest Jens Jenssønn Bloch og hustru og ukjent prestepar, Hadsel kirke, (1693)"
            },
            {
                "from_date": "",
                "order": "29",
                "to_date": "",
                "description": "bilder i Nes, Soknedal og Namdalseid kirker"
            },
            {
                "from_date": "",
                "order": "60",
                "to_date": "",
                "description": "Norsk Folkemuseum"
            },
            {
                "from_date": "",
                "order": "43",
                "to_date": "",
                "description": "sogneprest J.A. Borch (antagelig 1681, Glomdalsmuseet) og hustru Maren Opdal (antagelig 1681, Norsk Folkemuseum)"
            },
            {
                "from_date": "",
                "order": "53",
                "to_date": "",
                "description": "sogneprest S. Mogenssønn Blix, Dolstad kirke"
            },
            {
                "from_date": "",
                "order": "25",
                "to_date": "",
                "description": "epitafium Kvænangen kirke (1690, Historisk Museum Bergen)"
            },
            {
                "from_date": "",
                "order": "44",
                "to_date": "",
                "description": "sogneprest H.A. Bernhoft (?) og sogneprest Anders H. Bernhoft (?), Oppdal kirke (1680-årene)"
            },
            {
                "from_date": "",
                "order": "50",
                "to_date": "",
                "description": "sogneprest Peter Detlefsen, Røros kirke (1709)"
            },
            {
                "from_date": "",
                "order": "20",
                "to_date": "",
                "description": "epitafium Horg kirke (ca. 1679)"
            },
            {
                "from_date": "",
                "order": "34",
                "to_date": "",
                "description": "altertavle, prekestol og staffering Ålen kirke (1705)"
            },
            {
                "from_date": "",
                "order": "30",
                "to_date": "",
                "description": "altertavle og epitafium Rovde kirke (1700)"
            },
            {
                "from_date": "",
                "order": "59",
                "to_date": "",
                "description": "Historisk Museum Bergen"
            },
            {
                "from_date": "",
                "order": "55",
                "to_date": "",
                "description": "sogneprest C. Lossius, Tynset kirke"
            },
            {
                "from_date": "",
                "order": "40",
                "to_date": "",
                "description": "tavle fra altertavle Trysil kirke"
            },
            {
                "from_date": "",
                "order": "63",
                "to_date": "",
                "description": "Glomdalsmuseet"
            },
            {
                "from_date": "",
                "order": "24",
                "to_date": "",
                "description": "altertavle Tromsøysund kirke (1689)"
            },
            {
                "from_date": "",
                "order": "49",
                "to_date": "",
                "description": "ukjent prestepar på epitafium Rovde kirke (1700)"
            },
            {
                "from_date": "",
                "order": "35",
                "to_date": "",
                "description": "prekestol, Hessdalen kapell (1705)"
            },
            {
                "from_date": "",
                "order": "54",
                "to_date": "",
                "description": "sogneprest Anders Bredahl, Veøy kirke"
            },
            {
                "from_date": "",
                "order": "19",
                "to_date": "",
                "description": "altertavle (antagelig 1678) og epitafium øvre Rendal kirke (1679/81)"
            },
            {
                "from_date": "",
                "order": "64",
                "to_date": "",
                "description": "Vingelen kirke- og skolemuseum"
            },
            {
                "from_date": "",
                "order": "45",
                "to_date": "",
                "description": "sogneprest P.H. Ascanius, Aure kirke (antagelig 1690)"
            },
            {
                "from_date": "",
                "order": "39",
                "to_date": "",
                "description": "staffering, altertavle og malt gravstein over Ellen Henriksdatter Ravert (1709)"
            },
            {
                "from_date": "",
                "order": "27",
                "to_date": "",
                "description": "tilskrevet staffering, altertavle, døpefont og prekestol Rindal kirke (1694, inventar brent)"
            },
            {
                "from_date": "",
                "order": "31",
                "to_date": "",
                "description": "epitafier Herøy kirke (1700)"
            },
            {
                "from_date": "",
                "order": "58",
                "to_date": "",
                "description": "Det Kongelige Norske Videnskabers Selskab, Trondheim, Trondheim"
            },
            {
                "from_date": "",
                "order": "41",
                "to_date": "",
                "description": "Portretter attribuert til L. eller hans verksted: Hans Reinholdtsen Ohn, Lade kirke (1671)"
            },
            {
                "from_date": "",
                "order": "62",
                "to_date": "",
                "description": "Rørosmuseet"
            },
            {
                "from_date": "",
                "order": "56",
                "to_date": "",
                "description": "sogneprest E. Meyer, Orkdal kirke"
            },
            {
                "from_date": "",
                "order": "23",
                "to_date": "",
                "description": "bilde Vingelen kirke (1678)"
            },
            {
                "from_date": "",
                "order": "36",
                "to_date": "",
                "description": "altertavle Os kirke (1705, Glomdalsmuseet)"
            },
            {
                "from_date": "",
                "order": "48",
                "to_date": "",
                "description": "sogneprest Søren Hemstrup, Elverum kirke (1697)"
            },
            {
                "from_date": "",
                "order": "18",
                "to_date": "",
                "description": "Religiøse bilder og portretter i Røros gamle kirke (1671–73, 1705, deler overført til Røros kirke)"
            },
            {
                "from_date": "",
                "order": "38",
                "to_date": "",
                "description": "altertavle, prekestol og galleri Ranes kirke (1708, Det Kongelige Norske Videnskabers Selskab, Trondheim)"
            },
            {
                "from_date": "",
                "order": "46",
                "to_date": "",
                "description": "barnegruppe, (1690, Nordenfjeldske Kunstindustrimuseum, Trondheim)"
            }
        ],
        "performed_productions": [],
        "illustrations": [],
        "exhibitions": [],
        "portraits": [],
        "authorships": [],
        "publishings": [
            {
                "from_date": "1982",
                "order": "21",
                "reference": "bd. 3 s. 136 (ill.), 139",
                "to_date": "",
                "description": "Norges kunsthistorie",
                "place": "Oslo",
                "authors": [],
                "comments": [],
                "archives": []
            },
            {
                "from_date": "1933-09-23",
                "order": "5",
                "reference": "(ill.)",
                "to_date": "",
                "description": "i Dagsposten",
                "authors": [
                    "Brodahl, J. E"
                ],
                "comments": [],
                "archives": []
            },
            {
                "from_date": "1934-07-14",
                "order": "6",
                "to_date": "",
                "description": "i Dagsposten",
                "authors": [
                    "Brodahl, J. E"
                ],
                "comments": [],
                "archives": []
            },
            {
                "from_date": "1926",
                "order": "10",
                "reference": "s. 47 (ill.), 48–50",
                "to_date": "",
                "description": "Trøndermalere i Opdal kirke, Kunst og Kultur",
                "authors": [
                    "Brodahl, J. E."
                ],
                "comments": [],
                "archives": []
            },
            {
                "from_date": "1925",
                "order": "9",
                "reference": "ny rekke 2, s. 62–63 (ill.)",
                "to_date": "",
                "description": "Malte portrætter og billeder i Støren kirke, Trondhjemske Samlinger",
                "place": "Trondheim",
                "authors": [
                    "Brodahl, J. E."
                ],
                "comments": [],
                "archives": []
            },
            {
                "from_date": "1940",
                "order": "15",
                "reference": "register s. 321",
                "to_date": "",
                "description": "Norsk dekorativ maling fra reformasjonen til romantikken",
                "place": "Oslo",
                "authors": [
                    "Erdmann, D."
                ],
                "comments": [],
                "archives": []
            },
            {
                "from_date": "1932-08-20",
                "order": "13",
                "to_date": "",
                "description": "i Aftenposten",
                "authors": [
                    "Brodahl, J. E."
                ],
                "comments": [],
                "archives": []
            },
            {
                "from_date": "1922-06-10",
                "order": "3",
                "reference": "(ill.)",
                "to_date": "",
                "description": "i Dagsposten",
                "authors": [
                    "Brodahl, J. E"
                ],
                "comments": [],
                "archives": []
            },
            {
                "from_date": "1919-11-01",
                "order": "2",
                "reference": "(ill.)",
                "to_date": "",
                "description": "i Dagsposten",
                "authors": [
                    "Brodahl, J. E"
                ],
                "comments": [],
                "archives": []
            },
            {
                "from_date": "1973",
                "order": "20",
                "reference": "register bd. 2, s. 261",
                "to_date": "",
                "description": "Den lutherske ikonografi i Norge inntil 1800",
                "place": "Oslo",
                "authors": [
                    "Christie, S."
                ],
                "comments": [],
                "archives": []
            },
            {
                "from_date": "1935",
                "order": "14",
                "reference": "s. 22–23",
                "to_date": "",
                "description": "Tre århundres trøndersk maleri, Trondhjems Kunstforening 90-års skrift 17. desember 1935",
                "place": "Trondheim",
                "authors": [
                    "Brodahl, J. E."
                ],
                "comments": [],
                "archives": []
            },
            {
                "from_date": "1920",
                "order": "8",
                "reference": "register s. 153",
                "to_date": "",
                "description": "Malerkunsten i Norge i det attende aarhundre",
                "place": "(Kristiania",
                "authors": [
                    "Schnitler, C. W."
                ],
                "comments": [],
                "archives": []
            },
            {
                "from_date": "1919-05-17",
                "order": "1",
                "reference": "(ill.)",
                "to_date": "",
                "description": "i Dagsposten",
                "authors": [
                    "Brodahl, J. E"
                ],
                "comments": [],
                "archives": []
            },
            {
                "from_date": "1929",
                "order": "19",
                "reference": "bd. 23, s. 223",
                "to_date": "",
                "description": "Allgemeines Lexikon der bildenden Künstler",
                "place": "Leipzig",
                "authors": [
                    "Thieme-Becker"
                ],
                "comments": [],
                "archives": []
            },
            {
                "from_date": "1934-08-11",
                "order": "7",
                "reference": "(ill.)",
                "to_date": "",
                "description": "i Dagsposten",
                "authors": [
                    "Brodahl, J. E"
                ],
                "comments": [],
                "archives": []
            },
            {
                "from_date": "1947",
                "order": "17",
                "reference": "bd. 2, s. 99–103 (ill.)",
                "to_date": "",
                "description": "Strinda bygdebok",
                "place": "Trondheim",
                "authors": [],
                "comments": [],
                "archives": []
            },
            {
                "from_date": "1927",
                "order": "11",
                "reference": "bd. 2 register s. 676",
                "to_date": "",
                "description": "Norsk kunsthistorie",
                "place": "Oslo",
                "authors": [],
                "comments": [],
                "archives": []
            },
            {
                "from_date": "1943-06-12",
                "order": "16",
                "to_date": "",
                "description": "i Adresseavisen",
                "authors": [
                    "Brodahl, J. E."
                ],
                "comments": [],
                "archives": []
            },
            {
                "from_date": "1963",
                "order": "18",
                "reference": "s. 344",
                "to_date": "",
                "description": "Foreningen til norske Fortidsminnesmerkers Bevarings årbok",
                "place": "Sarpsborg",
                "authors": [],
                "comments": [
                    "register bd."
                ],
                "archives": []
            },
            {
                "from_date": "1922-11-11",
                "order": "4",
                "reference": "(ill.)",
                "to_date": "",
                "description": "i Dagsposten",
                "authors": [
                    "Brodahl, J. E"
                ],
                "comments": [],
                "archives": []
            },
            {
                "from_date": "1918-12-08",
                "order": "0",
                "to_date": "",
                "description": "i Dagsposten",
                "authors": [
                    "Brodahl, J. E"
                ],
                "comments": [],
                "archives": []
            },
            {
                "from_date": "1928",
                "order": "12",
                "reference": "register s. 340",
                "to_date": "",
                "description": "Norsk malerkunst under renessanse og barokk",
                "place": "Oslo",
                "authors": [
                    "Grevenor, H."
                ],
                "comments": [],
                "archives": []
            }
        ],
        "archives": [
            {
                "from_date": "1980",
                "order": "23",
                "reference": "(ill.)",
                "to_date": "",
                "description": "Dekorativt interiørmaleri i hjemmene i Os og Tolga fra 1740- til 1840-tallet",
                "authors": [
                    "Kvilhaug, I. Reitan"
                ],
                "comments": [
                    "dr. ing.avh."
                ],
                "archives": [
                    "Universitetet i Trondheim, Norges Tekniske Høyskole"
                ]
            },
            {
                "from_date": "",
                "order": "22",
                "to_date": "",
                "authors": [
                    "Joh. E. Brodahls"
                ],
                "comments": [
                    "arkiv om trøndermalere"
                ],
                "archives": [
                    "Antikvarisk arkiv, Riksantikvaren"
                ]
            }
        ],
        "radio_and_tv_programs": []
    },
    "title": "Peter Anderssønn Lillie",
    "url": "https://nkl.snl.no/Peter_Anderss%C3%B8nn_Lillie",
    "subject_url": "http://snl.no/.taxonomy/3405",
    "subject_title": "Norsk kunstnerleksikon",
    "xhtml_body": "<div>\n<p>L. var tidens mest produktive trondhjemsmaler. Arbeider av ham er kjent fra Elverum i sør, nord over Østerdalen, Møre og Romsdal, Trøndelagsfylkene til Kvænangen i Troms. L. er kjent som kirke- og portrettmaler, men han er også attribuert profant interiørmaleri. Muligens kan enkelte arbeider tillagt L. være utført av andre samtidige trøndermalere f.eks. broren Gustav eller Barak Bogarth, som han stilmessig kan ligne til forveksling. På den annen side kan L. tilskrives andre arbeider fra tiden, bevarte eller bare kjent fra kirkeregnskaper. Hans første kjente arbeider er utført på Røros i 1671–73, der kirken ble staffert og forsynt med \"Historrier udi Contrafei\". Et portrett av <em>Direktør Lorentz Lossius</em> er muligens av L. fra samme tidsrom. Fra 1671 fins et portrett i Lade kirke av <em>Hans Reinholdtsen Ohn</em> påmalt \"Hr. Henrich\" i senere år. Presten holder en beslått salmebok i høyre hånd, mens venstre hånd peker på en oppslått bok. Trekkene er typiske og gjennomgående i en rekke portretter av L. Et annet kjennetegn er halvlangt hår i lokker over kragen. Karaktertegningen er klar og malemåten omhyggelig. Dette er antagelig et eksempel på L.s stil før påvirkningen fra trønderstilen, som man mener Seth Bogarth har utviklet. Farge- og valørovergang er mindre kontrasterende enn i typisk trøndersk barokkmaleri. Trolig har L. på dette tidspunkt nylig kommet til Trøndelag østfra i strømmen av svenske innvandrere som søkte arbeid i tilknytning til gruvedriften på Røros. Han reiste mye i disse trakter, fra Trondheim opp Gauldalen, over Røros og sørover i Østerdalen. En <em>korsfestelsestavle</em> fra Vingelen kirke (1678) har rolig, relativt lys fargeholdning, mens tegningen av ansiktsprofiler i den sørgende hovedgruppe er typisk for L.s religiøse bilder. Her fins også kunstnerens vanlige sky- og treformasjoner. Rammen er signert med en bokstavgruppe som kan oppløses til signaturen PASL. <em>Prekestol</em> og en <em>tavle med Jesu dåp</em> har lignende fargeholdning og formgivning. Fra samme tidsrom stammer en <em>gjestestue</em> med dekorativ maling på vegger og tak på <em>Ustu Røe</em>, en nabogård til Vingelen kirke. Takmaleriet som er bevart, er et tidstypisk Hälsinglandsk rankemaleri i hvit, grå, sort og rød limfarge; hypotesen om L.s svenske avstamning bygger på funnet av hälsingranken i umiddelbar nærhet av L.s kirkemaleri. Trær, ansikts- og figurformer på <em>altertavlen i Øvre Rendal kirke</em> ligner dem på prekestolen i Vingelen og er trolig malt på turen i 1678. I 1679/81 var L. i Elverum, malte et <em>epitafium for Maren Opdal</em> og stafferte i kirken. Før denne tid har han hatt kontakt med trondhjemsmalerne, idet vi ser et samarbeid med Niels Nielsen om en <em>dommedagstavle fra korskillet i Horg kirke</em> (Det Kongelige Norske Videnskabers Selskab, Trondheim) med typiske stiltrekk fra begge malerne. Nielsens mørke konturer er vanlig for trøndermalerne og skulle bli det for L. </p>\n<p>I 1770-årene var et stilskifte i gang hos L. Han malte et <em>epitafium med dommedagsmotiv for Leinstrand (Nypan) kirke</em> (1675, Det Konglige Norske Videnskabers Selskab, Trondheim), et <em>Getsemanemotiv for Haltdalen kirke</em> (1678, Det Kongelige Norske Videnskabers Selskab, Trondheim) og et <em>epitafium med Jesus som preker fra båten for Horg kirke</em> (1679). Kirkeregnskapene i domkirken og Vår Frue kirke i Trondheim og i bygdene omkring nevner stadig L., domkirkens fra 1680. Han var etablert i byen på 1680-tallet, tok borgerskap og kjøpte gårder i Vår Frue sogn og på Kalvskinnet. L. var stadig på reiser, i Mørefylkene og i Nord-Trøndelag, på slutten av 1600-tallet og etter 1700. Hans største sammenhengende billedfrise er fra pasjonshistorien og er malt på <em>galleribrystningen i Vuku kirke</em> (1699) samtidig med <em>altertavle</em> (delvis overmalt), <em>prekestol</em> (rester bevart) og <em>korskille</em>. L. malte på nytt i kirkebygdene ved Gaulas og Glommas dalfører etter århundreskiftet på trøndersk barokkmaner med mettede og tildels mørke farger, stor farge- og valørkontrast og typisk ansiktsforming med fyldige kinn og høyrød markering av enkeltformer. Ifølge regnskap malte han i Melhus kirke ca. 1706. Derfra stammer <em>Kristus som smertensmenneske</em> (Det Kongelige Norske Videnskabers Selskab, Trondheim). Bildet med det sjeldne motivet i norsk malerkunst, er gjennomarbeidet uten det impresjonistiske anstrøket som er typisk i mye av trønderbarokken. Forbildet er trolig et maleri fra ca. 1550 i Trondheim domkirke, beslektet med Lucas Cranachs arbeider. Samme motiv i Nes kirke er trolig også av L. Karakteristisk er Jesu vemodsfylte blikk. L. hadde stort motivregister. De vanligste motiver var hentet fra pasjonshistorien, av nadverden har han laget en rekke varianter, utført med dyktighet. L. stafferte i tradisjonen etter Seth Bogarth, med lysende umalt tre som grunnmotiv, effektfull, rik fargesetting og velberegnet plassering av sølv- og gullbelegg. L.s portretter er av vekslende kvalitet, de beste viser en helhetlig holdning, slående menneskeskildring og staselig verdighet, mens en rekke er preget av rutinemessig masseproduksjon av standardtyper, utført som verkstedarbeid med tilføyelser av ansikt og hode på stedet.</p>\n</div>",
    "created_at": "2013-07-04T05:25:31.448+02:00",
    "changed_at": "2024-06-18T23:26:24.834+02:00",
    "license_name": "begrenset",
    "metadata_license_name": "fri",
    "metadata": {
        "gender": "m",
        "same_as": "[\"http://data.nasjonalmuseet.no/resource/person_8736ab2391\",\"https://digitaltmuseum.no/421ca0ae-7d5f-4d25-b679-b3e77dc69063\",\"http://kulturnav.org/421ca0ae-7d5f-4d25-b679-b3e77dc69063\"]",
        "lastname": "Lillie",
        "firstname": "Peter Anderssønn",
        "birthplace": "muligens i Hälsingland, Sverige",
        "death_date": "12.6.1711",
        "external_id": "person_8736ab2391",
        "kulturnav_id": "421ca0ae-7d5f-4d25-b679-b3e77dc69063",
        "place_of_death": "Trondheim",
        "alternative_names": "Lillie, Peter"
    },
    "authors": [
        {
            "full_name": "Ingeborg Reitan"
        }
    ],
    "images": [],
    "professions": [
        {
            "description": "kontrafeier"
        }
    ]
}