{
    "id": 418003,
    "headword": "Thoralf Nikolai Lerdal",
    "custom_metadata_json": {
        "professions": [
            {
                "description": "maler"
            },
            {
                "description": "tegner"
            }
        ],
        "others": [],
        "relations": [],
        "residences": [],
        "educations": [
            {
                "comment": "elev av Gerhard Munthe",
                "order": "1"
            },
            {
                "comment": "Statens Håndverks- og Kunstindustriskole, Oslo",
                "order": "0"
            },
            {
                "comment": "Statens Kunstakademi, Kristiania under Chr. Krohg og Halfdan Strøm, antagelig hospitant før 1921",
                "order": "2"
            }
        ],
        "travels": [
            {
                "order": "4",
                "description": "Sverige"
            },
            {
                "order": "1",
                "description": "Benneches legat 1922"
            },
            {
                "order": "5",
                "description": "Danmark"
            },
            {
                "order": "6",
                "description": "England"
            },
            {
                "order": "0",
                "description": "Finnes legat 1919–20"
            },
            {
                "order": "2",
                "description": "Schäffers legat 1925"
            },
            {
                "order": "3",
                "description": "Studiereiser Paris 1919"
            }
        ],
        "memberships": [
            {
                "order": "2",
                "description": "viseformann, styremedlem Oslo Kunstforening"
            },
            {
                "order": "1",
                "description": "Stiftet Lillestrøm og Omegns Kunstforening, nestformann de første årene"
            },
            {
                "order": "4",
                "description": "monterte Norske kunstneres utstilling, Øya, Trondheim 1930"
            },
            {
                "order": "3",
                "description": "jurymedlem Høstutstillingen"
            },
            {
                "order": "0",
                "description": "Professor ved Statens Kunstakademi, Oslo 1944–45"
            }
        ],
        "awards": [],
        "public_productions": [
            {
                "from_date": "",
                "order": "3",
                "to_date": "",
                "description": "Amaldus Nielsens Museum, Arendal"
            },
            {
                "from_date": "",
                "order": "2",
                "to_date": "",
                "description": "Nasjonalgalleriet, Oslo"
            },
            {
                "from_date": "",
                "order": "4",
                "to_date": "",
                "description": "Oslo kommunes kunstsamlinger"
            }
        ],
        "performed_productions": [],
        "illustrations": [],
        "exhibitions": [
            {
                "category": "Separat",
                "exhibition_organizer": "Blomqvists Kunsthandel, Oslo",
                "from_date": "1919",
                "order": "1",
                "to_date": ""
            },
            {
                "category": "Separat",
                "exhibition_organizer": "Blomqvists Kunsthandel, Oslo",
                "from_date": "1920",
                "order": "2",
                "to_date": ""
            },
            {
                "category": "Separat",
                "exhibition_organizer": "Kristiania Kunstforening",
                "from_date": "1917",
                "order": "0",
                "to_date": ""
            },
            {
                "category": "Separat",
                "exhibition_organizer": "Oslo Kunstforening",
                "from_date": "1938",
                "order": "4",
                "to_date": ""
            },
            {
                "category": "Separat",
                "exhibition_organizer": "Blomqvists Kunsthandel, Oslo",
                "from_date": "1928",
                "order": "3",
                "to_date": ""
            },
            {
                "category": "Kollektiv",
                "from_date": "1932",
                "order": "8",
                "to_date": "",
                "title": "Høstutstillingen"
            },
            {
                "category": "Kollektiv",
                "from_date": "1923",
                "order": "7",
                "to_date": "1926",
                "title": "Høstutstillingen"
            },
            {
                "category": "Kollektiv",
                "exhibition_organizer": "Blomqvists Kunsthandel, Oslo",
                "from_date": "1917",
                "order": "10",
                "to_date": "",
                "title": "De unge"
            },
            {
                "category": "Kollektiv",
                "from_date": "1915",
                "order": "5",
                "to_date": "",
                "title": "Høstutstillingen"
            },
            {
                "category": "Kollektiv",
                "from_date": "1921",
                "order": "6",
                "to_date": "",
                "title": "Høstutstillingen"
            },
            {
                "category": "Kollektiv",
                "exhibition_organizer": "Blomqvists Kunsthandel, Oslo",
                "from_date": "1921",
                "order": "13",
                "to_date": ""
            },
            {
                "category": "Kollektiv",
                "exhibition_organizer": "Kristiania Kunstforening",
                "from_date": "1916",
                "order": "9",
                "to_date": "",
                "title": "De frie unge"
            },
            {
                "category": "Kollektiv",
                "exhibition_organizer": "Kristiania Kunstforening",
                "from_date": "1918",
                "order": "11",
                "to_date": "",
                "title": "vårutstilling"
            },
            {
                "category": "Kollektiv",
                "exhibition_organizer": "Kristiania Kunstforening",
                "from_date": "1924",
                "order": "12",
                "to_date": "",
                "title": "vårutstilling"
            }
        ],
        "portraits": [
            {
                "from_date": "",
                "order": "7",
                "to_date": "",
                "description": "samt flere selvportretter i olje"
            },
            {
                "from_date": "",
                "order": "5",
                "to_date": "",
                "description": "Tegning gjengitt i Verdens Gang 24.4.1919"
            },
            {
                "from_date": "",
                "order": "6",
                "to_date": "",
                "description": "selvportrett gjengitt i Tidens Tegn 4.10.1920"
            }
        ],
        "authorships": [],
        "publishings": [
            {
                "from_date": "1938-04-02",
                "order": "16",
                "to_date": "",
                "description": "Nationen",
                "authors": [],
                "comments": [],
                "archives": []
            },
            {
                "from_date": "1944-12-04",
                "order": "20",
                "to_date": "",
                "description": "Fritt Folk",
                "authors": [],
                "comments": [],
                "archives": []
            },
            {
                "from_date": "1920-10-22",
                "order": "12",
                "to_date": "",
                "description": "i Tidens Tegn",
                "authors": [
                    "Gauguin Pola"
                ],
                "comments": [],
                "archives": []
            },
            {
                "from_date": "1921-09-12",
                "order": "14",
                "to_date": "",
                "description": "i Aftenposten",
                "authors": [
                    "Svarstad, A. C."
                ],
                "comments": [],
                "archives": []
            },
            {
                "from_date": "1938-04-04",
                "order": "18",
                "to_date": "",
                "description": "Morgenbladet",
                "authors": [],
                "comments": [],
                "archives": []
            },
            {
                "from_date": "1953",
                "order": "23",
                "reference": "bd. 2, s. 61",
                "to_date": "",
                "description": "Norges billedkunst i det 19. og 20. århundre",
                "place": "Oslo",
                "authors": [
                    "Revold, R."
                ],
                "comments": [],
                "archives": []
            },
            {
                "from_date": "1919-04-26",
                "order": "3",
                "to_date": "",
                "description": "i Aftenposten",
                "authors": [
                    "Haug, K."
                ],
                "comments": [],
                "archives": []
            },
            {
                "from_date": "1980",
                "order": "27",
                "reference": "bd. 7, s. 559",
                "to_date": "",
                "description": "Aschehougs og Gyldendals store norske leksikon",
                "place": "Oslo",
                "authors": [],
                "comments": [],
                "archives": []
            },
            {
                "from_date": "1965",
                "order": "25",
                "reference": "register s. 394",
                "to_date": "",
                "description": "Norske portretter. Videnskapsmenn",
                "place": "Oslo",
                "authors": [],
                "comments": [],
                "archives": []
            },
            {
                "from_date": "1944-12-22",
                "order": "21",
                "reference": "(ill.)",
                "to_date": "",
                "description": "Fritt Folk",
                "authors": [],
                "comments": [],
                "archives": []
            },
            {
                "from_date": "1917-03-02",
                "order": "1",
                "to_date": "",
                "description": "i Dagbladet",
                "authors": [
                    "Nilssen Jappe"
                ],
                "comments": [],
                "archives": []
            },
            {
                "from_date": "1919-04-25",
                "order": "5",
                "to_date": "",
                "description": "i Tidens Tegn",
                "authors": [
                    "Gauguin Pola"
                ],
                "comments": [],
                "archives": []
            },
            {
                "from_date": "1920-10-08",
                "order": "11",
                "to_date": "",
                "description": "Nationen",
                "authors": [],
                "comments": [],
                "archives": []
            },
            {
                "from_date": "1919-04-26",
                "order": "7",
                "to_date": "",
                "description": "i Nationen",
                "authors": [
                    "Lone, E."
                ],
                "comments": [],
                "archives": []
            },
            {
                "from_date": "1919-05-06",
                "order": "8",
                "to_date": "",
                "description": "i Verdens Gang",
                "authors": [
                    "Øverland, A."
                ],
                "comments": [],
                "archives": []
            },
            {
                "from_date": "1920-10-04",
                "order": "9",
                "reference": "(ill.)",
                "to_date": "",
                "description": "Tidens Tegn",
                "authors": [],
                "comments": [],
                "archives": []
            },
            {
                "from_date": "1938-04-02",
                "order": "17",
                "to_date": "",
                "description": "Aftenposten",
                "authors": [],
                "comments": [],
                "archives": []
            },
            {
                "from_date": "1928-01-26",
                "order": "15",
                "to_date": "",
                "description": "i Aftenposten",
                "authors": [
                    "Haug, K."
                ],
                "comments": [],
                "archives": []
            },
            {
                "from_date": "1921-09-05",
                "order": "13",
                "to_date": "",
                "description": "i Dagbladet",
                "authors": [
                    "Nilssen Jappe"
                ],
                "comments": [],
                "archives": []
            },
            {
                "from_date": "1938-09-04",
                "order": "19",
                "to_date": "",
                "description": "i Aftenposten",
                "authors": [
                    "Willoch, S."
                ],
                "comments": [],
                "archives": []
            },
            {
                "from_date": "1916-06-03",
                "order": "0",
                "to_date": "",
                "description": "i Dagbladet",
                "authors": [
                    "Nilssen Jappe"
                ],
                "comments": [],
                "archives": []
            },
            {
                "from_date": "1919-04-24",
                "order": "2",
                "reference": "(ill.)",
                "to_date": "",
                "description": "Verdens Gang",
                "authors": [],
                "comments": [],
                "archives": []
            },
            {
                "from_date": "1956",
                "order": "24",
                "reference": "register s. 278",
                "to_date": "",
                "description": "Norske portretter. Forfattere",
                "place": "Oslo",
                "authors": [],
                "comments": [],
                "archives": []
            },
            {
                "from_date": "1944",
                "order": "22",
                "reference": "s. 150 (ill.)",
                "to_date": "",
                "description": "Illustrert Norsk Kunstnerleksikon",
                "place": "Oslo",
                "authors": [],
                "comments": [],
                "archives": []
            },
            {
                "from_date": "1971",
                "order": "26",
                "reference": "s. 220",
                "to_date": "",
                "description": "Kunst og Kultur register 1910–67",
                "place": "Oslo",
                "authors": [],
                "comments": [],
                "archives": []
            },
            {
                "from_date": "1920-10-05",
                "order": "10",
                "to_date": "",
                "description": "i Dagbladet",
                "authors": [
                    "Nilssen Jappe"
                ],
                "comments": [],
                "archives": []
            },
            {
                "from_date": "1919-04-25",
                "order": "6",
                "to_date": "",
                "description": "Morgenposten",
                "authors": [],
                "comments": [],
                "archives": []
            },
            {
                "from_date": "1919-04-24",
                "order": "4",
                "to_date": "",
                "description": "i Dagbladet",
                "authors": [
                    "Nilssen Jappe"
                ],
                "comments": [],
                "archives": []
            }
        ],
        "archives": [
            {
                "from_date": "",
                "order": "28",
                "to_date": "",
                "authors": [],
                "comments": [],
                "archives": [
                    "Nasjonalgalleriets dokumentasjonsarkiv"
                ]
            }
        ],
        "radio_and_tv_programs": []
    },
    "title": "Thoralf Nikolai Lerdal",
    "url": "https://nkl.snl.no/Thoralf_Nikolai_Lerdal",
    "subject_url": "http://snl.no/.taxonomy/3405",
    "subject_title": "Norsk kunstnerleksikon",
    "xhtml_body": "<div><p>L. var utdannet billedskjærer før han ble maler. Han virket mest som portrettmaler og tegner og leverte i en årrekke portrettegninger til Aftenposten. L.s debutarbeide på Høstutstillingen i 1915 minnet om van Gogh, men senere arbeider bar bud om hans store beundring for Rembrandt og de gamle mestre. Portrettene hadde ofte en mørk galleritone, og landskapsbildene var stillferdige og enkle, litt romantiske naturskildringer. Nasjonalgalleriet, Oslo eier portrettet av <em>Antikvitetshandler Tv. Groseth</em> (1922) og Oslo kommune portrettet av <em>Amaldus Nielsen</em> (1931).</p></div>",
    "created_at": "2013-07-04T04:44:57.817+02:00",
    "changed_at": "2024-06-18T23:26:24.201+02:00",
    "license_name": "begrenset",
    "metadata_license_name": "fri",
    "metadata": {
        "gender": "m",
        "same_as": "[\"http://data.nasjonalmuseet.no/resource/person_8736ab2364\",\"https://digitaltmuseum.no/3544596a-f524-46f3-bbb1-877e337b02f6\",\"http://kulturnav.org/3544596a-f524-46f3-bbb1-877e337b02f6\"]",
        "lastname": "Lerdal",
        "firstname": "Thoralf Nikolai",
        "birth_date": "3.4.1888",
        "birthplace": "Lillestrøm",
        "death_date": "16.6.1961",
        "external_id": "person_8736ab2364",
        "kulturnav_id": "3544596a-f524-46f3-bbb1-877e337b02f6",
        "place_of_death": "Oslo"
    },
    "authors": [
        {
            "full_name": "Glenny Alfsen"
        }
    ],
    "images": [],
    "professions": [
        {
            "description": "maler"
        },
        {
            "description": "tegner"
        }
    ]
}