{
    "id": 416159,
    "headword": "Kjell Aukrust",
    "custom_metadata_json": {
        "professions": [
            {
                "description": "tegner"
            },
            {
                "description": "forfatter"
            }
        ],
        "others": [],
        "relations": [
            {
                "type": "Sønn av",
                "external_id": "person_8736ab100399",
                "birth_date": "",
                "death_date": "",
                "firstname": "O.",
                "lastname": "Lars",
                "professions": []
            },
            {
                "type": "Gift med",
                "external_id": "person_8736ab100401",
                "birth_date": "",
                "death_date": "",
                "firstname": "Kari",
                "lastname": "Holter",
                "professions": []
            },
            {
                "type": "Sønn av",
                "external_id": "person_8736ab100400",
                "birth_date": "",
                "death_date": "",
                "firstname": "Lovise",
                "lastname": "Aukrust",
                "professions": []
            }
        ],
        "residences": [],
        "educations": [
            {
                "comment": "Statens Håndverks- og Kunstindustriskole, Oslo under Per Krohg 1938-42",
                "order": "0"
            }
        ],
        "travels": [
            {
                "order": "5",
                "description": "Syria"
            },
            {
                "order": "0",
                "description": "T.forb. stipend 1950"
            },
            {
                "order": "4",
                "description": "Spania"
            },
            {
                "order": "1",
                "description": "Studiereiser England"
            },
            {
                "order": "3",
                "description": "Italia"
            },
            {
                "order": "2",
                "description": "Frankrike"
            }
        ],
        "memberships": [
            {
                "order": "0",
                "description": "Medlem T.forb., styremedlem 1950-52, jurymedlem 1954, formann i ett år"
            },
            {
                "order": "1",
                "description": "medlem av Forfatterforeningen og Dramatikerforbundet"
            }
        ],
        "awards": [
            {
                "order": "0",
                "description": "1. premie i konkurranse om emblem for Norsk Bygdekunstlag"
            },
            {
                "order": "1",
                "description": "2. premie konkurranse om emblem for De VI. olympiske vinterleker"
            }
        ],
        "public_productions": [
            {
                "from_date": "",
                "order": "3",
                "to_date": "",
                "description": "Oslo kommunes kunstsamlinger"
            },
            {
                "from_date": "",
                "order": "2",
                "to_date": "",
                "description": "Riksgalleriet"
            },
            {
                "from_date": "",
                "order": "1",
                "to_date": "",
                "description": "Nasjonalgalleriet, Oslo"
            }
        ],
        "performed_productions": [],
        "illustrations": [
            {
                "from_date": "",
                "order": "9",
                "to_date": "",
                "description": "til eget forfatterskap se litteraturlisten under Eget forfatterskap"
            },
            {
                "from_date": "",
                "order": "4",
                "to_date": "",
                "description": "Illustrert en rekke bøker bl.a. O. Aukrust: Reisen i Jutulfjell, Oslo 1949"
            },
            {
                "from_date": "",
                "order": "7",
                "to_date": "",
                "description": "E. Østvedt: De norske jernbaners historie I-III, Oslo 1954"
            },
            {
                "from_date": "",
                "order": "8",
                "to_date": "",
                "description": "I. Seierstad og E. Østvedt: Skien bys historie I-III, Skien 1958-69"
            },
            {
                "from_date": "",
                "order": "5",
                "to_date": "",
                "description": "Nisser og småtroll, Oslo 1949"
            },
            {
                "from_date": "",
                "order": "6",
                "to_date": "",
                "description": "Asbjørnsen og Moe: Folkeeventyr I-II, Oslo 1951"
            }
        ],
        "exhibitions": [
            {
                "category": "Kollektiv",
                "from_date": "1954",
                "order": "5",
                "to_date": "",
                "title": "Høstutst."
            },
            {
                "category": "Kollektiv",
                "from_date": "1939",
                "order": "6",
                "to_date": "",
                "title": "T.forb. utst."
            },
            {
                "category": "Separat",
                "exhibition_organizer": "O. Pedersens forretningslokale, Elverum",
                "from_date": "1944",
                "order": "0",
                "to_date": ""
            },
            {
                "category": "Separat",
                "exhibition_organizer": "Gall. Tanum, Oslo",
                "from_date": "1977",
                "order": "1",
                "to_date": "",
                "title": "Muntre streker"
            },
            {
                "category": "Kollektiv",
                "from_date": "1940",
                "order": "2",
                "to_date": "",
                "title": "Høstutst."
            },
            {
                "category": "Kollektiv",
                "from_date": "1948",
                "order": "4",
                "to_date": "1951",
                "title": "Høstutst."
            },
            {
                "category": "Kollektiv",
                "from_date": "1945",
                "order": "3",
                "to_date": "",
                "title": "Høstutst."
            },
            {
                "category": "Kollektiv",
                "exhibition_organizer": "Kunstnerforbundet, Oslo",
                "from_date": "1954",
                "order": "9",
                "to_date": ""
            },
            {
                "category": "Kollektiv",
                "exhibition_organizer": "Kunstnerforbundet, Oslo",
                "from_date": "1946",
                "order": "7",
                "to_date": "",
                "title": "8 tegnere"
            },
            {
                "category": "Kollektiv",
                "exhibition_organizer": "Oslo Kunstforening",
                "from_date": "1951",
                "order": "8",
                "to_date": "",
                "title": "T.forb.s jub.utst."
            },
            {
                "category": "Kollektiv",
                "exhibition_organizer": "Kunstnernes Hus, Oslo",
                "from_date": "1957",
                "order": "10",
                "to_date": "",
                "title": "Nordiske tegnere"
            }
        ],
        "portraits": [],
        "authorships": [
            {
                "from_date": "1960",
                "order": "3",
                "to_date": "",
                "description": "Bror min",
                "place": "Oslo",
                "authors": [
                    "AUKRUST, Kjell"
                ],
                "comments": [],
                "archives": []
            },
            {
                "from_date": "1977",
                "order": "13",
                "to_date": "",
                "description": "Ludvig",
                "place": "Oslo",
                "authors": [
                    "AUKRUST, Kjell"
                ],
                "comments": [],
                "archives": []
            },
            {
                "from_date": "1964",
                "order": "5",
                "to_date": "",
                "description": "Bonden",
                "place": "Oslo",
                "authors": [
                    "AUKRUST, Kjell"
                ],
                "comments": [],
                "archives": []
            },
            {
                "from_date": "1968",
                "order": "7",
                "to_date": "",
                "description": "Relsa Fus",
                "place": "Oslo",
                "authors": [
                    "AUKRUST, Kjell"
                ],
                "comments": [],
                "archives": []
            },
            {
                "from_date": "1958",
                "order": "1",
                "to_date": "",
                "description": "Simen",
                "place": "Oslo",
                "authors": [
                    "AUKRUST, Kjell"
                ],
                "comments": [],
                "archives": []
            },
            {
                "from_date": "1976",
                "order": "11",
                "to_date": "",
                "description": "Melvin Snerken",
                "place": "Oslo",
                "authors": [
                    "AUKRUST, Kjell"
                ],
                "comments": [],
                "archives": []
            },
            {
                "from_date": "1973",
                "order": "9",
                "to_date": "",
                "description": "Hilsen Solan og Nystumoen",
                "place": "Oslo",
                "authors": [
                    "AUKRUST, Kjell"
                ],
                "comments": [],
                "archives": []
            },
            {
                "from_date": "1947",
                "order": "12",
                "to_date": "1975",
                "description": "Flåklypaserien I-VI",
                "place": "Oslo",
                "authors": [
                    "AUKRUST, Kjell"
                ],
                "comments": [],
                "archives": []
            },
            {
                "from_date": "1959",
                "order": "2",
                "to_date": "",
                "description": "Folk og fe",
                "place": "Oslo",
                "authors": [
                    "AUKRUST, Kjell"
                ],
                "comments": [],
                "archives": []
            },
            {
                "from_date": "1949",
                "order": "0",
                "to_date": "",
                "description": "Vesle Ola",
                "place": "Oslo",
                "authors": [
                    "Aukrust, Kjell"
                ],
                "comments": [],
                "archives": []
            },
            {
                "from_date": "1972",
                "order": "8",
                "to_date": "",
                "description": "Simen, Bonden og Bror min",
                "place": "Oslo",
                "authors": [
                    "AUKRUST, Kjell"
                ],
                "comments": [],
                "archives": []
            },
            {
                "from_date": "1966",
                "order": "6",
                "to_date": "",
                "description": "Je og 'n Solan",
                "place": "Oslo",
                "authors": [
                    "AUKRUST, Kjell"
                ],
                "comments": [],
                "archives": []
            },
            {
                "from_date": "1961",
                "order": "4",
                "to_date": "",
                "description": "Muskedunder og sirupssnipper",
                "place": "Oslo",
                "authors": [
                    "AUKRUST, Kjell"
                ],
                "comments": [
                    "(dramatisert)"
                ],
                "archives": []
            },
            {
                "from_date": "1975",
                "order": "10",
                "to_date": "",
                "description": "Dobbeltsats og freske fraspark",
                "place": "Oslo",
                "authors": [
                    "AUKRUST, Kjell"
                ],
                "comments": [
                    "(oppført på Det Norske Teatret 1975-76 og senere filmatisert)"
                ],
                "archives": []
            },
            {
                "from_date": "",
                "order": "14",
                "to_date": "",
                "description": "Flåklypa Grand Prix",
                "authors": [
                    "AUKRUST, Kjell"
                ],
                "comments": [
                    "og filmen av samme navn"
                ],
                "archives": []
            }
        ],
        "publishings": [
            {
                "from_date": "1974",
                "order": "21",
                "to_date": "",
                "description": "Slik var n'Kjell",
                "place": "Oslo",
                "authors": [
                    "Hoel, I."
                ],
                "comments": [],
                "archives": []
            },
            {
                "from_date": "1960",
                "order": "17",
                "to_date": "",
                "description": "Humor i Norden",
                "place": "Uddevalla",
                "authors": [],
                "comments": [],
                "archives": []
            },
            {
                "from_date": "1952-08-27",
                "order": "23",
                "to_date": "",
                "description": "Dagbladet",
                "authors": [],
                "comments": [],
                "archives": []
            },
            {
                "from_date": "1977-09-25",
                "order": "27",
                "to_date": "",
                "description": "Arbeiderbladet",
                "authors": [],
                "comments": [],
                "archives": []
            },
            {
                "from_date": "1977-09-15",
                "order": "25",
                "to_date": "",
                "description": "Verdens Gang",
                "authors": [],
                "comments": [],
                "archives": []
            },
            {
                "from_date": "1952",
                "order": "15",
                "to_date": "",
                "description": "Norsk Illustrasjonskunst 1850-1950",
                "place": "Oslo",
                "authors": [
                    "Sundseth, A.B.",
                    "Melhus, A.C."
                ],
                "comments": [],
                "archives": []
            },
            {
                "from_date": "1971",
                "order": "20",
                "to_date": "",
                "description": "Nytt norsk forfatterleksikon",
                "place": "Oslo",
                "authors": [
                    "Dahl, W."
                ],
                "comments": [],
                "archives": []
            },
            {
                "from_date": "1968",
                "order": "18",
                "to_date": "",
                "description": "AKL",
                "place": "Oslo",
                "authors": [],
                "comments": [],
                "archives": []
            },
            {
                "from_date": "1956",
                "order": "16",
                "to_date": "",
                "description": "Illustrert Norsk Kunstnerleksikon",
                "place": "Oslo",
                "authors": [],
                "comments": [],
                "archives": []
            },
            {
                "from_date": "1978",
                "order": "22",
                "reference": "s. 63",
                "to_date": "",
                "description": "K. og K.",
                "authors": [],
                "comments": [],
                "archives": []
            },
            {
                "from_date": "1975-08-28",
                "order": "24",
                "to_date": "",
                "description": "Dagbladet",
                "authors": [],
                "comments": [],
                "archives": []
            },
            {
                "from_date": "1978-02-25",
                "order": "28",
                "to_date": "",
                "description": "Adr.",
                "authors": [],
                "comments": [],
                "archives": []
            },
            {
                "from_date": "1977-09-22",
                "order": "26",
                "to_date": "",
                "description": "Morgenbladet",
                "authors": [],
                "comments": [],
                "archives": []
            },
            {
                "from_date": "1974",
                "order": "19",
                "to_date": "",
                "description": "Humor i Norge",
                "place": "Oslo",
                "authors": [
                    "Feldborg, A."
                ],
                "comments": [],
                "archives": []
            }
        ],
        "archives": [
            {
                "from_date": "1977",
                "order": "29",
                "to_date": "",
                "title": "Flåklypabøkene til Kjell Aukrust - En suksess, dens bakgrunn og utvikling",
                "authors": [
                    "Midtbø, T."
                ],
                "comments": [
                    "hovedoppgave"
                ],
                "archives": [
                    "Universitetsbiblioteket Oslo"
                ]
            }
        ],
        "radio_and_tv_programs": []
    },
    "title": "Kjell Aukrust",
    "url": "https://nkl.snl.no/Kjell_Aukrust",
    "subject_url": "http://snl.no/.taxonomy/3405",
    "subject_title": "Norsk kunstnerleksikon",
    "xhtml_body": "<div>\n<p>A. er vokst opp i fjellbygda Alvdal. Faren var bestyrer på Storteigen Landbruksskole og stortingsrepresentant for Bondepartiet. Miljøet fra barndommen har vært sterkt bestemmende for A.s forfatterskap og kunstneriske utvikling. Han var utdannet som snekker, men kom etter tilskyndelse fra Henrik Sørensen inn på Statens Håndverks- og Kunstindustriskole. Tegnet i Allers, Norsk Ukeblad, Aftenposten, Vårt Land, Dagbladet og Mannskapsavisa. Tekster og tegninger i Mannskapsavisa danner grunnlaget for Flåklypaserien i 6 bind, en grotesk parodi på norsk kulturdebatt og journalistikk.</p>\n<p>A.s forfatterskap, hvor tegningene utgjør det vesentlige innslag, er blitt allemannseie. Det representerer i all sin absurditet en samling kulturbilder som faller i 3 grupper: 1) barndomsopplevelser i Alvdal, 2) forfatterens voksne liv sammen med imaginære vesener, 3) Flåklypabøkene som skildrer et univers, befolket med underlige oppdiktede typer. I sine tegninger representerer han en høyst original form for intelligent crazy-humor og sarkasme. Den groteske overdrivelse har sin rot i folkelig virkelighet. Flettet inn blant karikaturene finnes nesten lyriske naturstemninger i slekt med hans illustrasjoner til billedboken Reisen i Jutulfjell (1949) og eventyrtegningene (1951).</p>\n<p>A.s illustrerte forfatterskap har ekspandert til andre media, dramatiseringer oppført på Det Norske Teatret, Flåyklypa radio 1959-60 og i TV 1971, samt helaftens dokkefilm i samarbeid med Ivo Caprino 1975. Denne har hatt suksess på det internasjonale marked.</p>\n<p>Statens Informasjonstjeneste har tatt figuren \"Ludvig\" i bruk for propagandaen for bruk av bilbelter og overholdelse av fartsgrenser.</p>\n</div>",
    "created_at": "2013-07-03T14:18:19.051+02:00",
    "changed_at": "2024-06-18T23:25:33.514+02:00",
    "license_name": "begrenset",
    "metadata_license_name": "fri",
    "metadata": {
        "gender": "m",
        "same_as": "[\"http://data.nasjonalmuseet.no/resource/person_8736ab199\",\"https://digitaltmuseum.no/710ba6b9-b742-413b-8d1f-a3e5824ec89f\",\"http://kulturnav.org/710ba6b9-b742-413b-8d1f-a3e5824ec89f\"]",
        "lastname": "Aukrust",
        "firstname": "Kjell",
        "birth_date": "19.3.1920",
        "birthplace": "Alvdal",
        "death_date": "24.12.2002",
        "external_id": "person_8736ab199",
        "kulturnav_id": "710ba6b9-b742-413b-8d1f-a3e5824ec89f",
        "place_of_death": "Oslo"
    },
    "authors": [
        {
            "full_name": "Sonja Hagemann"
        }
    ],
    "images": [],
    "professions": [
        {
            "description": "tegner"
        },
        {
            "description": "forfatter"
        }
    ]
}